<DATABASE_UI_LOCALIZATION-NO_HSH>
  <LOC_LIBRARY-UI>
    <Entry Key="QUOTE_MARKS_EXAMPLE" Val="„Przykład”" />
    <Entry Key="UI_GREET_PLAYER" Val="Pozdrowienia {SCRIPT:UIS_GetCurentPlayerName}!" />
    <Entry Key="UI_YOU_ARE_ABOUT_TO_DELETE_PROFILE" Val="Zamierzasz usunąć profil gracza: {SCRIPT:UIS_GetProfileToDelete}!" />
    <Entry Key="UI_SELECT_TARGETS" Val="Wybierz cele dla umiejętności {SCRIPT:UIS_TargetSelectionCount}" />
    <Entry Key="UI_SELECT_TARGETS_INVALID" Val="Wybierz cele dla umiejętności {SCRIPT:UIS_TargetSelectionCount}\nNieprawidłowe cele, umiejętność nie zostanie wykonana!" />
    <Entry Key="UI_EXPORTED_MODULE" Val="Wyeksportowany moduł '{SCRIPT:UIS_GlobalVar,ModuleSaveID}' do: \n{SCRIPT:UIS_GlobalVar,ModuleSaveDir}" />
    <Entry Key="UI_IMPORT_ERROR" Val="Błąd importu: {SCRIPT:UIS_GlobalVar,ErrorID}z modułu: \n{SCRIPT:UIS_GlobalVar,ErrorAtModule}, zdarzenie: {SCRIPT:UIS_GlobalVar,ErrorAtEvent}, węzeł: {SCRIPT:UIS_GlobalVar,ErrorAtNode}" />
    <Entry Key="UI_NONE" Val="Brak" />
    <Entry Key="UI_ADVENTURE_START_NODE" Val="Węzeł Rozpoczęcie przygody" />
    <Entry Key="UI_ADVENTURE_END_NODE" Val="Węzeł zakończenia przygody" />
    <Entry Key="UI_ADVENTURE_CHALLENGE_NODE" Val="Węzeł wyzwania" />
    <Entry Key="UI_ADVENTURE_NODE" Val="Węzeł przygody" />
    <Entry Key="UI_ADVENTURE_DEAL_DAMAGE_NODE" Val="Deal Damage Node" />
    <Entry Key="UI_ADVENTURE_SPAWN_NODE" Val="Węzeł spawnowania" />
    <Entry Key="UI_ADVENTURE_TRADE_NODE" Val="Węzeł handlowy" />
    <Entry Key="UI_MAKE_PUBLIC" Val="Zrób publiczny" />
    <Entry Key="UI_ENEMY_TURN" Val="Tura przeciwnika" />
    <Entry Key="UI_FRIENDLY_TURN" Val="Przyjazna tura" />
    <Entry Key="UI_AT_DELAY" Val="Opóźnienie" />
    <Entry Key="UI_BATTLE_RESOLVE" Val="Rozstrzyganie bitwy (1/2)" />
    <Entry Key="UI_BATTLE_RESOLVE_2" Val="Rozstrzyganie bitwy (2/2)" />
    <Entry Key="UI_NOT_A_FREE_SLOT" Val="To gniazdo nie jest bezpłatne!" />
    <Entry Key="UI_ANOTHER_PLAYER_TARGETTING" Val="Proszę czekać, inny gracz dokonuje wyboru ..." />
    <Entry Key="UI_WARNING" Val="Ostrzeżenie" />
    <Entry Key="UI_SAVE_OR_DISCARD" Val="Zapisz lub odrzuć zmiany?" />
    <Entry Key="UI_CONFIRM_AND_EXIT" Val="Zapisz i wyjdź" />
    <Entry Key="UI_DISCARD_AND_EXIT" Val="Odrzuć i wyjdź" />
    <Entry Key="UI_DONT_LEAVE" Val="Zostań i edytuj" />
    <Entry Key="UI_OK" Val="OK" />
    <Entry Key="UI_ERROR" Val="Błąd" />
    <Entry Key="UI_EXPORT_ERROR" Val="Wystąpił błąd, dane nie zostały wyeksportowane." />
    <Entry Key="UI_IMPORTED_MODULE" Val="Moduł został pomyślnie zaimportowany." />
    <Entry Key="UI_SET_SERVER_NAME" Val="Ustaw nazwę serwera" />
    <Entry Key="UI_CONFIRM" Val="Potwierdź" />
    <Entry Key="UI_CANCEL" Val="Anuluj" />
    <Entry Key="UI_NAME_CANNOT_BE_EMPTY" Val="Nazwa nie może być pusta." />
    <Entry Key="UI_GOD_POINTS" Val="God Points: " />
    <Entry Key="UI_SINGLE_PLAYER" Val="Single Player" />
    <Entry Key="UI_MULTIPLAYER" Val="Multiplayer" />
    <Entry Key="UI_EVENTS_EDITOR" Val="Edytor zdarzeń" />
    <Entry Key="UI_SETTINGS" Val="Ustawienia" />
    <Entry Key="UI_QUIT" Val="Zakończ" />
    <Entry Key="UI_CONTINUE" Val="Kontynuuj" />
    <Entry Key="UI_NEW_GAME" Val="Nowa gra" />
    <Entry Key="UI_LOAD_GAME" Val="Załaduj grę" />
    <Entry Key="UI_BACK" Val="Powrót" />
    <Entry Key="UI_HOST_NEW_GAME" Val="Host - Nowa gra" />
    <Entry Key="UI_HOST_LOAD" Val="Host - Ładuj" />
    <Entry Key="UI_JOIN" Val="Dołącz" />
    <Entry Key="UI_PICK_A_PROFILE" Val="Wybierz profil" />
    <Entry Key="UI_NEW_PROFILE" Val="Nowy profil" />
    <Entry Key="UI_RENAME_PROFILE" Val="Zmień nazwę profilu" />
    <Entry Key="UI_DELETE_PROFILE" Val="Usuń profil" />
    <Entry Key="UI_SELECT" Val="Wybierz" />
    <Entry Key="UI_DOMAINS" Val="Domeny" />
    <Entry Key="UI_GOD_CARD_SLOTS" Val="God Card Slots" />
    <Entry Key="UI_SPELL" Val="Zaklęcie" />
    <Entry Key="UI_NEXT" Val="Dalej" />
    <Entry Key="UI_SELECT_YOUR_GOD" Val="Wybierz swojego Boga" />
    <Entry Key="UI_RESOLVING_CURRENT_STACK" Val="Rozwiązywanie bieżącego stosu ..." />
    <Entry Key="UI_END_TURN" Val="Zakończ turę" />
    <Entry Key="UI_SELECT_MODULE_TO_CLONE_TO" Val="Wybierz moduł do sklonowania:" />
    <Entry Key="UI_EVENTS" Val="Zdarzenia" />
    <Entry Key="UI_OF" Val="z" />
    <Entry Key="UI_BACK_TO_MODULES" Val="Powrót do modułów" />
    <Entry Key="UI_EDIT_EVENT" Val="Edytuj wydarzenie" />
    <Entry Key="UI_MAKE_A_SELECTION" Val="Dokonaj wyboru…" />
    <Entry Key="UI_BACK_TO_EVENTS" Val="Powrót do wydarzeń" />
    <Entry Key="UI_ADD_A_NODE" Val="Dodaj węzeł" />
    <Entry Key="UI_ADVENTURE" Val="Przygoda" />
    <Entry Key="UI_CHALLENGE" Val="Wyzwanie" />
    <Entry Key="UI_SPAWN_ON_MAP" Val="Pomiot na mapie" />
    <Entry Key="UI_PRODUCE_DROP" Val="Produkuj Drop" />
    <Entry Key="UI_ADVENTURE_PRODUCE_DROP_NODE" Val="Spadek produkcji" />
    <Entry Key="UI_TRADE" Val="Handel" />
    <Entry Key="UI_DEAL_DAMAGE" Val="Zadaj obrażenia" />
    <Entry Key="UI_ADVENTURE_END" Val="Koniec przygody" />
    <Entry Key="UI_SEARCH" Val="Wyszukaj…" />
    <Entry Key="UI_SELECT_AN_IMAGE" Val="Wybierz obraz" />
    <Entry Key="UI_IMAGE_SIZE" Val="Rozmiar obrazu:" />
    <Entry Key="UI_IMAGE_SIZE_NOTES" Val="Uwaga: Optymalny rozmiar obrazu to &lt;b&gt; 700x1000px &lt;/b&gt;. Można również stosować inne rozmiary o podobnym współczynniku proporcji. Używanie obrazu o różnych proporcjach spowoduje zniekształcenie obrazu. \nAby dodać nowe obrazy do tej listy, umieść je w folderze &lt;b&gt; StreamingAssets EventGraphics &lt;/b&gt; znajdującym się w folderze gry. &lt;b&gt; Używaj tylko formatów .png lub .jpg!&lt;/b&gt;" />
    <Entry Key="UI_LOGIC_EDITOR" Val="Edytor logiki" />
    <Entry Key="UI_FILTERS" Val="Filtry" />
    <Entry Key="UI_PROCESSING" Val="Przetwarzanie" />
    <Entry Key="UI_RESULTS" Val="Wyniki" />
    <Entry Key="UI_EXIT_LOGIC" Val="Wyjdź z logiki" />
    <Entry Key="UI_SELECT_A_MODULE" Val="Edytor zdarzeń - wybierz moduł" />
    <Entry Key="UI_MODULES" Val="Moduły" />
    <Entry Key="UI_EXIT_AND_SAVE" Val="Wyjdź i zapisz" />
    <Entry Key="UI_EDIT_MODULE" Val="Edytuj moduł" />
    <Entry Key="UI_ENTER_QUEST_NAME" Val="Nazwa misji (Loc String)" />
    <Entry Key="UI_ENTER_QUEST_DESCRIPTION" Val="Opis zadania (Loc String)" />
    <Entry Key="UI_SHOW_IN_LOGBOOK" Val="Pokaż w dzienniku" />
    <Entry Key="UI_PICK_A_TAG" Val="Wybierz tag" />
    <Entry Key="UI_TURN" Val="Tura:" />
    <Entry Key="UI_TURN2" Val="Tura" />
    <Entry Key="UI_INVENTORY" Val="Inwentaryzacja" />
    <Entry Key="UI_FILTER" Val="Filtruj…" />
    <Entry Key="UI_SORT" Val="Sortuj…" />
    <Entry Key="UI_SUPPLIES" Val="Dostawy" />
    <Entry Key="UI_TRANSFER" Val="Transfer" />
    <Entry Key="UI_TRANSFER_FOOD" Val="Transfer żywności" />
    <Entry Key="UI_VARIETIES_FOR" Val="odmiany dla" />
    <Entry Key="UI_DAYS" Val="dni" />
    <Entry Key="UI_PERCENT_OF_ALL_AVAILABLE_FOOD" Val="% całej dostępnej żywności" />
    <Entry Key="UI_RAW_FOOD" Val="Surowe jedzenie" />
    <Entry Key="UI_COOKED_FOOD" Val="Gotowane jedzenie" />
    <Entry Key="UI_JOIN_A_MULTIPLAYER_GAME" Val="Dołącz do gry wieloosobowej" />
    <Entry Key="UI_REPORT_A_BUG" Val="Zgłoś błąd" />
    <Entry Key="UI_REPORT_A_BUG1" Val="Użyj tego formularza, aby zgłosić problem z grą. Zrzut ekranu gry i pliku dziennika zostanie dołączony do tego raportu wraz z komentarzem i wysłany do naszego narzędzia do śledzenia błędów. Nie gromadzimy żadnych danych osobowych." />
    <Entry Key="UI_REPORT_A_BUG2" Val="Proszę opisać swój problem z jak największą ilością szczegółów w poniższym polu. Jeśli to możliwe, uwzględnij kroki do odtworzenia, które znacznie zwiększają szansę naprawienia problemu dla nas." />
    <Entry Key="UI_REPORT_A_BUG3" Val="Dziękujemy za poświęcenie czasu na napisanie tego raportu!" />
    <Entry Key="UI_REPORT_A_BUG4" Val="- Miłość, zespół MuHa Games" />
    <Entry Key="UI_TITLE" Val="Tytuł" />
    <Entry Key="UI_BUG_DESC_HERE" Val="Opis błędu tutaj." />
    <Entry Key="UI_SEND" Val="Wyślij" />
    <Entry Key="UI_IGNORE" Val="Ignoruj" />
    <Entry Key="UI_CONNECTION_OPTIONS" Val="Opcje połączenia" />
    <Entry Key="UI_CONNECTION_TYPE" Val="Typ połączenia:" />
    <Entry Key="UI_CONNECTION_PORT" Val="Port połączenia:" />
    <Entry Key="UI_SELECT_CONNECTION_TYPE" Val="Wybierz typ połączenia…" />
    <Entry Key="UI_IP_AND_PORT" Val="Adres IP i port:" />
    <Entry Key="UI_PORT_EXAMPLE" Val="tj. 9999" />
    <Entry Key="UI_IP_AND_PORT_EXAMPLE" Val="tj. 192.168.0.1:9999" />
    <Entry Key="UI_SERVER_NAME" Val="Nazwa serwera:" />
    <Entry Key="UI_ENTER_NAME" Val="Wprowadź nazwę…" />
    <Entry Key="UI_ENTER_NEW_NAME" Val="Wprowadź nazwę…" />
    <Entry Key="UI_ENTER_NEW_NAME_INFO" Val="Wprowadź nazwę w polu poniżej." />
    <Entry Key="UI_PASSWORD" Val="Hasło (opcjonalnie):" />
    <Entry Key="UI_ENTER_PASSWORD" Val="Wprowadź hasło ..." />
    <Entry Key="UI_REGION_PREFERENCE" Val="Preferencja regionu: \n(brak dla automatycznego)" />
    <Entry Key="UI_SELECT_REGION" Val="Wybierz region ..." />
    <Entry Key="UI_CONNECTION_STATUS" Val="Status połączenia:" />
    <Entry Key="UI_LOADING" Val="Ładowanie ..." />
    <Entry Key="UI_DZIEVANNA" Val="Dzievanna" />
    <Entry Key="UI_DZIEVANNA_DES" Val="Idę w czujnym cieniu starej matki ziemi, która milczy. Słucham jej szeptów i śpiewam jej piosenki. Pani lasów, duch natury, pani ziemi - tak nazywają mnie śmiertelnicy. Ale nie dajcie się zwieść pięknu mojej domeny, pragnieniu utrzymania równowagi życia i skarbu ponad wszystko. \n\nNatura nie jest twoją spokojną matką. Przekrocz moją ścieżkę, sprzeciwiając się odwiecznym prawom i poznasz furię lasów. Bo ja też jestem łowczynią. Cichy i czujny, wierny mojej sprawie i niezachwiany w moim postanowieniu. Zniszcz moją domenę na własne ryzyko i poczuj szept lasu na twoim ramieniu, zanim śmierć przyjdzie po ciebie! \n\nChodź ze mną wśród drzew, jeśli się odważysz." />
    <Entry Key="UI_HORZ" Val="Horz" />
    <Entry Key="UI_HORZ_DES" Val="Z cienia nocy i przerażenia ciemności, które zawsze czai się w rogach, wstaję! Odradzając się na nowo w splotach magii księżyca, stoję jako mistrz nocy i strażnik księżyca. Potwory, bestie, demony i diabły, które przemierzają moją domenę. Ode mnie zależy, czy będą je kontrolować, aby rządzić, dominować i niszczyć tych, którzy nie przestrzegają! \n\nJestem prześladowcą cieni, wyjec w nocy. Biegam z wilkami i tańczę z gwiazdami. Rządzę ciemnością, aby upewnić się, że światło nie zwycięży wszystkich. Jest to zadanie niekochające, samotne i okrutne, ale jest to ścieżka, którą będę kroczyć tak długo, jak księżyc będzie wisiał na niebie. \n\nNie bój się ciemności, opanuj to!" />
    <Entry Key="UI_LADA" Val="Lada" />
    <Entry Key="UI_LADA_DES" Val="Urodziłem się w najciemniejszej godzinie naszej ziemi, z ziarna nadziei w sercach naszych ludzi. Długa noc miała na celu zmniejszenie wszelkiego światła i miłości z naszych serc, ale nie mogła tego zrobić. Pod nieobecność ojca, który kiedyś nas prowadził, i matki, która była naszym opiekunem, teraz stoję na czele naszego panteonu, tak że nadzieja pozostaje w czasach nieustającego zawirowania. \n\nNie myl mnie z tym, że delikatny kwiat szuka tylko żyznej ziemi, by wyrosnąć na nim nasiona. Piękno i nadzieja mogą jeszcze zamienić ich kwitnące płatki w odłamki stali i grzmoty, gdy nadejdzie odpowiedni czas. Droga pokoju rzadko jest spokojna. \n\nAle jeśli twoje serce bije mocno, a twoja wola jest z żelaza, dołącz do mnie na drodze do harmonii." />
    <Entry Key="UI_MAROVIT" Val="Marovit" />
    <Entry Key="UI_MAROVIT_DES" Val="Mądrość i wiedza płyną w niestabilnych prądach przez nasz świat, a ja jestem ich uczniem. Nie szukam dominacji ani nie twierdzę, że trzymam lejce takich rzek, nie. Umysł i dusza na zawsze pozostaną tajemnicami, a my, czy to śmiertelnicy czy wieczni, możemy tylko patrzeć na powierzchnię wielkich oceanów zrozumienia. \n\nDuchowy piechur, mędrzec, strażnik kluczy wiedzy i mistycyzmu - to imiona dziecinnie związane z moimi domenami. Jestem jedynie sługą woli oceanu, samotnym marynarzem, który stara się oświecić innych. Śmiertelnicy zapominają, że nie są mistrzami naszych ziem, zapominają o nich lub je odrzucają, ale ja jestem tutaj, aby przypomnieć im całą moc innych światów. \n\nSzukaj mądrości, nie lękaj się nieznanego, dzierź sploty magii jako swój miecz." />
    <Entry Key="UI_NYIA" Val="Nyia" />
    <Entry Key="UI_NYIA_DES" Val="Zapomniany, opuszczony, pomniejszony, sam ... Przez wieki byłem tylko zwykłym wspomnieniem ... Nie nawet tego. Ale pani zimy już nie ma, mistrza podziemi już nie ma. I wreszcie znów zajmuję swoje miejsce. Mistrzyni śmierci, zwiastunka smutku, opiekunka pocieszenia i śmierci. \n\nTylko ja mogę przemierzać ziemie umarłych - navy, tylko ja mogę nieść dusze wiernych do ich domów i pokoju. Jednak nie jest to usługa dobrze przyjęta. Nie opłakuję zmarłych, nie płaczę nad umierającymi, wszystko jest tak, jak powinno być, tak jak zostało stworzone - a czasami, kiedy prawa są łamane, śmierć będzie obsługiwana przez moją rękę. Cierpiałem w ciemności. Teraz nieskończenie przynoszę cierpienie i jego koniec. \n\nDołącz do mnie? Dlaczego, głupcze?" />
    <Entry Key="UI_STRIBOG" Val="Stribog" />
    <Entry Key="UI_STRIBOG_DES" Val="Świat się rozpadł, ziemia się poruszyła, a oceany zalały nasze domy. Nie możemy już zostać w jednym miejscu, musimy się ruszyć, podbić, zbadać! Z wiatrów północy noszę lodową wolę walki. Z wiatrów zachodnich będę błogosławił twoje podróże z szybkością. Z prądów wschodnich będę szeptać mądrość, a dzięki ciepłemu uścisku południowego wiatru zapewniam komfort podczas podróży. \n\nByłem kiedyś duchem wiatrów, wolnym, dzikim i nieokiełznanym - ale usłyszałem wołanie kosmicznego drzewa, gdy ziemia się pod nim rozsypała. Zostałem wezwany przez moich braci i siostry, zostałem wezwany przez mój lud, który podniósł ręce do nieba i poprosił o dobre wiatry. Jestem teraz bogiem podróży, tropicielem, dawcą ścieżki i przewodnikiem. \n\nChodź ze mną na wiatry i poznaj prawdziwą wolność." />
    <Entry Key="UI_SVAROG" Val="Svarog" />
    <Entry Key="UI_SVAROG_DES" Val="Z płomieni nieba i popiołów z przeszłości ciemności wstaję do mego obowiązku! Bóg słońca i mistrz niebiańskich pożarów - to mój zaszczyt znieść. Ale kiedy kiedyś dzierżyłem strój wojownika, teraz znam prawdziwą moc światła i ognia, proste ognisko, które oświetla domy i serca mojej trzody. \n\nTo nie moc bogów uratuje nasze ziemie, ale moc, którą możemy dać naszym wiernym. W palących płomieniach mojej domeny powstają narzędzia i broń prawdziwych bohaterów, śmiertelników i nieśmiertelnych, przysięgających podtrzymać moją żelazną wolę. \n\nChroń tych, którzy są w potrzebie, nigdy się nie wycofuj, nigdy się nie poddawaj i nigdy więcej nie pozwól ciemności rządzić światłem!" />
    <Entry Key="UI_TRIGLAV" Val="Triglav" />
    <Entry Key="UI_TRIGLAV_DES" Val="Argh! From the scorching lava seeping out of the ashes of our land, I was forged! Veins of wrath pulsate throughout my body with rage and purpose. My stone hearts beat in unison, my minds meld into one vision, my fists are driven trifold. I do not know who raised me from the darkness. I do not know why our hearts melt with anger, but I am ready to stand and fight against any who will dare to oppose us!\n\nA new force rises to devour Thea once again and I will stand in its way. This is why I have risen from fire. Walk with me into war, burn our enemies to the ground, melt away those who seek to wound us, crush whoever stands in the path of divine justice and wrath.\n\nAnd you? You are to bow before me and obey!" />
    <Entry Key="UI_ZORYA" Val="Zorya" />
    <Entry Key="UI_ZORYA_DES" Val="Mój ojciec twierdzi, że ma prawo być mistrzem światła i słońca, ale to my jedziemy na niebie w nieskończoność! Gwiazda poranna wznosi się daleko i wyblakła, jest subtelna i zawsze czujna wobec swoich wrogów. Gwiazda południa wisi nisko i ciężko, gotowa do walki i pożerania wrogów. Wieczorna gwiazda rozświetla niebo i przygotowuje się na wojnę! Zorya, Zorza, Auroras, wszystkie imiona nadane nam przez tych, którzy są na tyle odważni, by ich śledzić! \n\nJestem jasnym ostrzem nocy i lśniącą rękawicą dnia. Trzymam bestię, która pożre nasz świat w mojej dłoni i śmieję się w obliczu wroga. Bądź odważny, brutalny i szybki. \n\nWrogowie równowagi znów rosną w siłę, rozerwę ich na strzępy i pochłonę ich wnętrzności! Dołącz do mnie!" />
    <Entry Key="UI_LOAD_A_SAVED_GAME" Val="Załaduj zapisaną grę" />
    <Entry Key="UI_SAVED_GAMES" Val="Zapisane gry" />
    <Entry Key="UI_GAME_SETTINGS" Val="Ustawienia gry" />
    <Entry Key="UI_GAME_VERSION" Val="Wersja gry:" />
    <Entry Key="UI_LOAD" Val="Załaduj" />
    <Entry Key="UI_MULTIPLAYER_LOBBY" Val="Lobby dla wielu graczy" />
    <Entry Key="UI_PLAYERS" Val="Gracze" />
    <Entry Key="UI_ENTER_MESSAGE" Val="Wpisz wiadomość…" />
    <Entry Key="UI_LEAVE" Val="Wyjdź" />
    <Entry Key="UI_START" Val="Rozpocznij" />
    <Entry Key="UI_SAVE" Val="Zapisz" />
    <Entry Key="UI_ENTER_SAVE_NAME" Val="Wpisz Zapisz nazwę…" />
    <Entry Key="UI_SAVE_GAME" Val="Zapisz grę" />
    <Entry Key="UI_WORLD_SETTINGS" Val="Ustawienia świata" />
    <Entry Key="UI_DIFFICULTY_SETTINGS" Val="Ustawienia trudności" />
    <Entry Key="UI_NEXT" Val="Dalej" />
    <Entry Key="UI_BONUSES" Val="Premie" />
    <Entry Key="UI_BUILDINGS" Val="Budynki" />
    <Entry Key="UI_TASKS" Val="Zadania" />
    <Entry Key="UI_CLOSE" Val="Zamknij" />
    <Entry Key="UI_MANAGE_EQUIPMENT" Val="Zarządzaj sprzętem" />
    <Entry Key="UI_ATTRIBUTES" Val="Atrybuty" />
    <Entry Key="UI_SKILLS" Val="Umiejętności" />
    <Entry Key="UI_SUBSKILLS" Val="Podkwalifikacje" />
    <Entry Key="UI_INNATE" Val="Wrodzona" />
    <Entry Key="UI_FROM_EQUIPMENT" Val="Od sprzętu" />
    <Entry Key="UI_PASSIVE_EFFECTS" Val="Efekty" />
    <Entry Key="UI_NOTES" Val="Uwagi" />
    <Entry Key="UI_RESOURCES_RECOVERED" Val="Odzyskane zasoby:" />
    <Entry Key="UI_ITEM_RECYCLED" Val="Przedmiot poddany recyklingowi!" />
    <Entry Key="UI_WAITING_FOR_SERVER" Val="Oczekiwanie na serwer ..." />
    <Entry Key="UI_NONE" Val="Brak" />
    <Entry Key="UI_SCRIPT" Val="Skrypt" />
    <Entry Key="UI_PARAMETER1" Val="Parametr 1" />
    <Entry Key="UI_PARAMETER2" Val="Parametr 2" />
    <Entry Key="UI_ENTER_A_NUMBER" Val="Wprowadź numer ..." />
    <Entry Key="UI_AZ_SORT" Val="Sortuj od A do Z" />
    <Entry Key="UI_GATHERING_CHARACTER_SORT" Val="Sortuj według zbierania" />
    <Entry Key="UI_COUNT_SORT" Val="Sortuj według liczby" />
    <Entry Key="UI_TYPE_SORT" Val="Sortuj według typu" />
    <Entry Key="UI_NO_FILTER" Val="Brak filtra" />
    <Entry Key="UI_WEAPONS_FILTER" Val="Broń" />
    <Entry Key="UI_ARMOURS_FILTER" Val="Zbroje" />
    <Entry Key="UI_SORT_BY" Val="Sortuj według" />
    <Entry Key="UI_FILTER_BY" Val="Filtruj według" />
    <Entry Key="UI_DIFFICULTY_HINT" Val="Trudność Wskazówka" />
    <Entry Key="UI_DIALOGUE_GROUP" Val="Grupa dialogu" />
    <Entry Key="UI_ASSIGN_TRAITS" Val="Przypisz cechy" />
    <Entry Key="UI_BENEFITS_COST_LESS" Val="Korzyści z domen twojego boga kosztują mniej." />
    <Entry Key="UI_START_GAME" Val="Rozpocznij grę" />
    <Entry Key="UI_POWER_POINTS_LEFT" Val="Pozostało punktów mocy: {SCRIPT:UIS_GlobalVar,GodPowerPointsLeft}" />
    <Entry Key="UI_HOST_A_MULTIPLAYER_GAME" Val="Hostuj grę wieloosobową" />
    <Entry Key="UI_ENTER_LOGIC_EDITOR" Val="Wprowadź Edytor logiki" />
    <Entry Key="UI_ADD_NEW_OUTPUT" Val="Dodaj nowe wyjście" />
    <Entry Key="UI_ANSWER_TEXT" Val="Odbierz tekst ..." />
    <Entry Key="UI_SET_IMAGE" Val="Ustaw obraz" />
    <Entry Key="UI_XP_FOR_CURRENT_PLAYER" Val="XP dla obecnego gracza:" />
    <Entry Key="UI_RP_FOR_CURRENT_PLAYER" Val="RP dla obecnego gracza:" />
    <Entry Key="UI_XP_FOR_ALL_PLAYERS" Val="XP dla wszystkich graczy:" />
    <Entry Key="UI_RP_FOR_ALL_PLAYERS" Val="RP dla wszystkich graczy:" />
    <Entry Key="UI_NAVIGATE_TO_ADVENTURE" Val="Nawiguj do przygody:" />
    <Entry Key="UI_CHALLENGE_TYPE" Val="Typ wyzwania:" />
    <Entry Key="UI_AUTOSCALE_BY_ENEMY" Val="Autoskalowanie przez wroga:" />
    <Entry Key="UI_VS_EVENT_OWNER" Val="Versus Event Owner:" />
    <Entry Key="UI_VS_GROUP" Val="Versus Group:" />
    <Entry Key="UI_CHALLENGE_SCALE" Val="Skala wyzwania:" />
    <Entry Key="UI_CHALLENGE_LIST" Val="Lista wyzwań:" />
    <Entry Key="UI_FROM_EVENT_OWNER" Val="Z właściciela wydarzenia:" />
    <Entry Key="UI_FROM_GROUP" Val="Z grupy:" />
    <Entry Key="UI_DMG_SOURCE_COUNT" Val="Liczba źródeł Dmg:" />
    <Entry Key="UI_CHALLENGED_LIST" Val="Lista wyzwań:" />
    <Entry Key="UI_CARGO_PERCENTAGE" Val="Procent spadku ładunku:" />
    <Entry Key="UI_DROP_CARGO_PERCENTAGE" Val="Procent upuszczenia ciała:" />
    <Entry Key="UI_TARGET_GROUP" Val="Grupa docelowa:" />
    <Entry Key="UI_SPAWN_SOURCE_GROUP" Val="Spawn Source Group:" />
    <Entry Key="UI_SPAWN_SOURCE_SETTLEMENT" Val="Spawn Source Settlement:" />
    <Entry Key="UI_DESTROY_EVENT_OWNER" Val="Destroy Event Owner:" />
    <Entry Key="UI_MIN_RADIUS" Val="Minimalny promień:" />
    <Entry Key="UI_BIOME" Val="Biome:" />
    <Entry Key="UI_LINKED_EVENT" Val="Powiązane wydarzenie:" />
    <Entry Key="UI_EVENT_TYPE" Val="Typ zdarzenia:" />
    <Entry Key="UI_INTERRUPT" Val="Przerwij" />
    <Entry Key="UI_GENERIC" Val="Ogólne" />
    <Entry Key="UI_GROUP_GENERIC" Val="Generic grupy" />
    <Entry Key="UI_EXPEDITION" Val="Ekspedycja" />
    <Entry Key="UI_VILLAGE" Val="Wioska" />
    <Entry Key="UI_DIFFICULTY" Val="Trudność:" />
    <Entry Key="UI_SUBSKILL_INFO" Val="Subskill Info" />
    <Entry Key="UI_LEVEL" Val="Poziom" />
    <Entry Key="UI_LEGEND" Val="Legenda" />
    <Entry Key="UI_MOUSE_ZOOM_OUT" Val="Środkowy przycisk myszy - pomniejszenie" />
    <Entry Key="UI_DONT_SHOW_AGAIN" Val="Nie pokazuj więcej" />
    <Entry Key="UI_UNSPENT_AP" Val="Niewykorzystane punkty akcji" />
    <Entry Key="UI_UNSPENT_AP1" Val="Czy na pewno chcesz zakończyć swoją turę? \nNadal masz kilka punktów akcji!" />
    <Entry Key="UI_UNSPENT_AP2" Val="Niewykorzystane punkty akcji zostaną przeniesione do następnej fazy przygotowawczej." />
    <Entry Key="UI_ASSIGN" Val="Przypisz" />
    <Entry Key="UI_COOKING_AND_COMPOSITES" Val="Gotowanie i kompozyty" />
    <Entry Key="UI_CRAFTING" Val="Crafting" />
    <Entry Key="UI_EXPLORING" Val="Eksplorowanie" />
    <Entry Key="UI_AVAILABLE_WORKERS" Val="Dostępne pracowników" />
    <Entry Key="UI_TASKS" Val="Zadania" />
    <Entry Key="UI_FAVOURITES" Val="Ulubione" />
    <Entry Key="UI_COOKING_MODE" Val="Tryb gotowania" />
    <Entry Key="UI_NEW_TASK" Val="Nowe zadanie" />
    <Entry Key="UI_ASSIGN_WORKERS" Val="Przydziel pracowników do rozpoczęcia" />
    <Entry Key="UI_CREATE_NEW_ITEM" Val="Utwórz nowy element" />
    <Entry Key="UI_COMPATIBLE_RESOURCES" Val="Kompatybilne zasoby" />
    <Entry Key="UI_PRIMARY_MATERIAL" Val="Materiał podstawowy" />
    <Entry Key="UI_SECONDARY_MATERIAL" Val="Materiał pomocniczy" />
    <Entry Key="UI_ASSIGN_A_SKILL" Val="Przypisz umiejętność" />
    <Entry Key="UI_INVITE_OTHER_PLAYERS_TO_EVENT" Val="Zaproś innych graczy na to wydarzenie?" />
    <Entry Key="UI_INVITE" Val="Zaproś" />
    <Entry Key="UI_JOINED" Val="Dołączył" />
    <Entry Key="UI_JOIN_AN_EVENT" Val="Dołącz do wydarzenia" />
    <Entry Key="UI_WAITING" Val="Czekam ..." />
    <Entry Key="UI_REFUSED" Val="Odmowa" />
    <Entry Key="UI_EVENT_PARTICIPATION" Val="Udział w wydarzeniu:" />
    <Entry Key="UI_JOINING_IS_FORCED" Val="Łączenie jest wymuszone" />
    <Entry Key="UI_INCLUDE_ALL_PLAYERS" Val="Wszyscy gracze" />
    <Entry Key="UI_INCLUDE_NEARBY_ALLY_GROUPS" Val="Pobliskie grupy sojuszników" />
    <Entry Key="UI_INCLUDE_NEARBY_OWN_GROUPS" Val="W pobliżu własne grupy" />
    <Entry Key="UI_JOINING_RANGE" Val="Zakres łączenia" />
    <Entry Key="UI_JOINING_TYPE" Val="Typ grupy łączenia" />
    <Entry Key="UI_EVENT_ID" Val="Identyfikator zdarzenia:" />
    <Entry Key="UI_NODE_SEARCH" Val="Wyszukiwanie węzła ..." />
    <Entry Key="UI_TRADER_PROFILE" Val="Profil inwestora:" />
    <Entry Key="UI_SELLING_LIST" Val="Lista sprzedaży:" />
    <Entry Key="UI_STARTING_BALANCE" Val="Bilans początkowy:" />
    <Entry Key="UI_ALL_CHARACTERS" Val="Wszystkie znaki" />
    <Entry Key="UI_TAGS" Val="Tagi" />
    <Entry Key="UI_PRIMARY_RESOURCE" Val="Podstawowa" />
    <Entry Key="UI_SECONDARY_RESOURCE" Val="Drugorzędny" />
    <Entry Key="UI_REFINED" Val="Wyrafinowany" />
    <Entry Key="UI_UNLOCK_CONFIRMATION" Val="{COLOR:#42C100}Kliknij przycisk POTWIERDŹ, aby odblokować." />
    <Entry Key="UI_UNLOCK_RESOURCE_CONFIRMATION" Val="Odblokowanie tego zasobu pozwoli Twoim ludziom go zebrać. Twój Wybrany otrzyma również 10 jednostek tego zasobu." />
    <Entry Key="UI_UNLOCK_ITEM_CONFIRMATION1" Val="Odblokowanie tego przepisu pozwoli Twojemu ludowi wykonać następujące przedmioty:" />
    <Entry Key="UI_UNLOCK_ITEM_CONFIRMATION2" Val="Odblokowanie tego przepisu pozwoli twoim ludziom na wykonanie następujących przedmiotów i zapewnienie premii za 5% esencji:" />
    <Entry Key="UI_UNLOCK_ITEM_CONFIRMATION3" Val="Odblokowanie tego przepisu jeszcze bardziej uszczegółowi projekt przedmiotu, dodając 20% do każdej esencji użytej w jego tworzeniu." />
    <Entry Key="UI_UNLOCK_ITEM_CONFIRMATION4" Val="Odblokowanie da ci umiejętności pokazane poniżej. Mogą być przypisane do przedmiotu, gdy zostanie on wytworzony." />
    <Entry Key="UI_UNLOCK_ITEM_CONFIRMATION5" Val="Odblokuje również umiejętności pokazane poniżej, które można przypisać do przedmiotu, gdy zostanie wykonany." />
    <Entry Key="UI_ESSENCE_BONUS1" Val="Bonus Essence: 5%" />
    <Entry Key="UI_UNLOCK_BUILDING_CONFIRMATION1" Val="Odblokowanie tej struktury pozwoli Twoim ludziom skonstruować ją przy użyciu następujących typów materiałów:" />
    <Entry Key="UI_UNLOCK_RITUAL_CONFIRMATION1" Val="Odblokowanie tego rytuału pozwoli twoim ludziom wykonać go przy użyciu następujących rodzajów materiałów:" />
    <Entry Key="UI_UNLOCK_FOOD_CONFIRMATION" Val="Odblokowanie tego przepisu żywnościowego pozwoli twoim ludziom gotować potrawy przy użyciu następujących surowych rodzajów żywności:" />
    <Entry Key="UI_ADVANCEMENT_RESOURCES" Val="Awansowanie - zasoby" />
    <Entry Key="UI_ADVANCEMENT_EQUIPMENT" Val="Awansowanie - wyposażenie" />
    <Entry Key="UI_ADVANCEMENT_FOOD" Val="Postęp - Żywność" />
    <Entry Key="UI_ADVANCEMENT_BUILDINGS_AND_RITUALS" Val="Awans - Budynki i rytuały" />
    <Entry Key="UI_ADVANCEMENT_SKILLS" Val="Awans - Umiejętności" />
    <Entry Key="UI_COST" Val="Koszt: " />
    <Entry Key="UI_UNLOCKED_SKILLS" Val="Odblokowane umiejętności" />
    <Entry Key="UI_ADVANCEMENT_POINTS" Val="Punkty awansu" />
    <Entry Key="UI_REROLL_SETS" Val="Ponownie rzutuj zestawy" />
    <Entry Key="UI_NOT_ENOUGH_RP" Val="{COLOR:#C80000}Nie masz wystarczającej liczby punktów awansu, aby to odblokować." />
    <Entry Key="UI_ALL_PARENT_RESOURCES_REQUIRED" Val="{COLOR:#C80000}Musisz najpierw odblokować wszystkie postępy rodzica." />
    <Entry Key="UI_WORKBENCH" Val="Workbench" />
    <Entry Key="UI_DESIGN" Val="Projektowanie" />
    <Entry Key="UI_DESIGN_MODE" Val="Tryb projektowania" />
    <Entry Key="UI_DESIGN_MODE_ON" Val="Tryb projektowania włączony" />
    <Entry Key="UI_RESEARCH_AND_RITUALS" Val="Badania i rytuały" />
    <Entry Key="UI_RESEARCH" Val="Badania" />
    <Entry Key="UI_RITUALS" Val="Rytuały" />
    <Entry Key="UI_SPEND_POINTS" Val="Wydaj punkty" />
    <Entry Key="UI_ALREADY_UNLOCKED" Val="{COLOR:#5B80FF}Już odblokowałeś ten awans!" />
    <Entry Key="UI_NEARBY_RESOURCES" Val="Zasoby w pobliżu" />
    <Entry Key="UI_GATHERING" Val="Zbieranie" />
    <Entry Key="UI_BUILD_VER" Val="Kompilacja v. " />
    <Entry Key="UI_BUILD_VERSION" Val="Kompilacja v. " />
    <Entry Key="UI_FOOD_MANAGEMENT" Val="Zarządzanie żywnością" />
    <Entry Key="UI_FUEL_MANAGEMENT" Val="Zarządzanie paliwem" />
    <Entry Key="UI_FUEL_MANAGEMENT" Val="Zarządzanie paliwem" />
    <Entry Key="UI_FOOD_BONUSES" Val="Premie za żywność" />
    <Entry Key="UI_LOCATIONS" Val="Lokalizacje" />
    <Entry Key="UI_ADVENTURE" Val="Przygoda" />
    <Entry Key="UI_PICK_A_RECIPE" Val="Wybierz przepis" />
    <Entry Key="UI_BASE_VALUE" Val="Wartość bazowa:" />
    <Entry Key="UI_BONUSES_LOSES" Val="Premie / straty:" />
    <Entry Key="UI_MULTIPLIER" Val="Mnożnik:" />
    <Entry Key="UI_FINAL_VALUE" Val="Wartość końcowa:" />
    <Entry Key="UI_MODIFIERS" Val="Modyfikatory" />
    <Entry Key="UI_CRAFTING_SORT" Val="Sortuj według Wytwarzanie" />
    <Entry Key="UI_GATHERING_SORT" Val="Sortuj według gromadzenia" />
    <Entry Key="UI_RITUALS_SORT" Val="Sortuj według wartości Rytuałów" />
    <Entry Key="UI_LOADING_MODULES" Val="Ładowanie modułów ..." />
    <Entry Key="UI_ESSENCES" Val="Esencje" />
    <Entry Key="UI_AMOUNT" Val="Kwota:" />
    <Entry Key="UI_MIN_DMG" Val="Minimalne obrażenia:" />
    <Entry Key="UI_MAX_DMG" Val="Maksymalne obrażenia:" />
    <Entry Key="UI_DAMAGE_AS_PERCENT" Val="Uszkodzenie jako procent" />
    <Entry Key="UI_LEFT_CLICK_DISMANTLE" Val="(Lewy przycisk - Demontaż)" />
    <Entry Key="UI_YOUR_GROUP" Val="Twoja grupa:" />
    <Entry Key="UI_ENEMY_GROUP" Val="Enemy Group:" />
    <Entry Key="UI_VERSUS" Val="VS." />
    <Entry Key="UI_AUTO_RESOLVE" Val="Auto Resolve" />
    <Entry Key="UI_BEGIN" Val="Zacznij!" />
    <Entry Key="UI_PHYSICAL_CHALLENGE" Val="Wyzwanie fizyczne" />
    <Entry Key="UI_MENTAL_CHALLENGE" Val="Wyzwanie mentalne" />
    <Entry Key="UI_SPIRITUAL_CHALLENGE" Val="Wyzwanie duchowe" />
    <Entry Key="UI_PASSIVE_BONUSES" Val="Efekty pasywne" />
    <Entry Key="UI_VS_CONCEPT" Val="Koncepcja VS" />
    <Entry Key="UI_SELECT_RECIPE" Val="Wybierz przepis" />
    <Entry Key="UI_PICK_ONE" Val="Wybierz jeden atrybut dla każdej postaci." />
    <Entry Key="UI_LEVEL_UP" Val="Poziom wyżej" />
    <Entry Key="UI_NEW" Val="Nowość!" />
    <Entry Key="UI_PAUSE_MENU" Val="Menu pauzy" />
    <Entry Key="UI_RESUME" Val="Wznów" />
    <Entry Key="UI_QUIT_TO_MENU" Val="Wyjdź do menu" />
    <Entry Key="UI_UNLOCK" Val="Odblokuj" />
    <Entry Key="UI_DRAG_AND_DROP_TRAIT" Val="Przeciągnij i upuść tutaj Cechę, aby ją wybrać" />
    <Entry Key="UI_ALLOW_NEW_FOOD" Val="Zezwalaj na używanie nowych produktów spożywczych" />
    <Entry Key="UI_ALLOW_NEW_FUEL" Val="Zezwalaj na używanie nowych elementów paliwowych" />
    <Entry Key="UI_USE_RAW_FOOD" Val="Użyj surowej żywności" />
    <Entry Key="UI_USE_COOKED_FOOD" Val="Użyj gotowanego jedzenia" />
    <Entry Key="UI_FORFEIT_HEADING" Val="Wyzwanie przepadku" />
    <Entry Key="UI_FORFEIT_CHALLENGE" Val="Czy na pewno chcesz zrezygnować z tego wyzwania? Jeśli to zrobisz, mogą wystąpić złe konsekwencje." />
    <Entry Key="UI_FACTIONS_AND_LOYALTY" Val="Frakcje i lojalność" />
    <Entry Key="UI_GODS_CHOSEN" Val="Wybrany przez Boga" />
    <Entry Key="UI_CHARACTER_CLASS" Val="Klasa postaci" />
    <Entry Key="UI_MORE" Val="Więcej" />
    <Entry Key="UI_MORE2" Val="więcej" />
    <Entry Key="UI_TUTORIAL_CAST1" Val="Granie kartą" />
    <Entry Key="UI_TUTORIAL_CAST2" Val="Zacznij od grania w karty z {COLOR:yellow}}na {END_COLOR}Battlefield {COLOR:yellow}. Oto jak to zrobić:" />
    <Entry Key="UI_TUTORIAL_CAST3" Val="1. Kliknij kartę." />
    <Entry Key="UI_TUTORIAL_CAST4" Val="2. Wybierz umiejętność." />
    <Entry Key="UI_TUTORIAL_CAST5" Val="3. Wybierz gniazdo, w które chcesz rzucić." />
    <Entry Key="UI_TUTORIAL_DESIGN_MODE1" Val="Tryb projektowania pozwala wypróbować dowolną badaną recepturę i zapisać ją jako ulubioną do późniejszego użycia. \n\nTwój ekwipunek pokazuje teraz wszystkie materiały rzemieślnicze obecne w grze, nawet te, których nie masz. \n\nZapraszam do eksperymentowania!" />
    <Entry Key="UI_TUTORIAL_DESIGN_MODE2" Val="Możesz dodać przepis do listy zadań rzemieślniczych, naciskając Potwierdź. \n\nPrace nad nim można rozpocząć tylko wtedy, gdy masz {COLOR:yellow}wymagane materiały {END_COLOR}w ekwipunku." />
    <Entry Key="UI_TUTORIAL_MOVE1" Val="Poruszanie się" />
    <Entry Key="UI_TUTORIAL_MOVE2" Val="Aby przenieść swoją grupę z jednej płytki na drugą: \n\n1. Kliknij lewym przyciskiem myszy grupę, aby ją wybrać, \n2. Naciśnij i przytrzymaj RMB nad innym kafelkiem. \n\nPodróżowanie zużywa {COLOR:yellow}punkty ruchu {END_COLOR}({ICON:MPIcon}) w zależności od rodzaju terenu." />
    <Entry Key="UI_TUTORIAL_CAMERA1" Val="Sterowanie kamerą" />
    <Entry Key="UI_TUTORIAL_CAMERA2" Val="Możesz przesuwać kamerę za pomocą klawiatury {COLOR:yellow}(WASD lub klawiszy strzałek) {END_COLOR}lub naciskając {COLOR:yellow}środkowy przycisk myszy {END_COLOR}." />
    <Entry Key="UI_CHECK_EQUIPMENT1" Val="Sprawdź wyposażenie" />
    <Entry Key="UI_CHECK_EQUIPMENT2" Val="Zanim podejdziesz do niebezpieczeństw Thea, spójrz na swój {COLOR:yellow}Sprzęt {END_COLOR}i przypisz swoim postaciom niewykorzystane przedmioty, które mogą nosić. \n\nKliknij grupę, aby otworzyć menu promieniowe {COLOR:yellow}i naciśnij przycisk Equip." />
    <Entry Key="UI_TUTORIAL_END_TURN1" Val="Kończenie swojej tury" />
    <Entry Key="UI_TUTORIAL_END_TURN2" Val="Po zakończeniu działań naciśnij przycisk {COLOR:yellow}Koniec zakrętu {END_COLOR}znajdujący się w prawym dolnym rogu ekranu." />
    <Entry Key="UI_TUTORIAL_END_TURN3" Val="Wiele rzeczy dzieje się pomiędzy twoimi turami: \n\n- grupy kontrolowane przez komputer wykonują swoje działania, \n- różne zadania są rozwijane, \n- zdarzają się pewne wydarzenia przygodowe, \n- ranne postacie odzyskują zdrowie itp" />
    <Entry Key="UI_RESOURCES" Val="Zasoby" />
    <Entry Key="UI_TUTORIAL_CAMP1" Val="Istnieją różne typy {COLOR:yellow}zasobów {END_COLOR}na świecie. Mogą być użyte jako {COLOR:yellow}materiały rzemieślnicze, żywność lub paliwo {END_COLOR}, ale zanim twoi ludzie będą mogli z nich korzystać - muszą je zebrać." />
    <Entry Key="UI_TUTORIAL_CAMP2" Val="Zasoby są wyświetlane na mapie świata jako specjalne obiekty, takie jak rośliny, zwierzęta, kości itp." />
    <Entry Key="UI_TUTORIAL_CAMP3" Val="Przesuń swoją grupę w pobliżu płytki z zasobem znajdującym się nie dalej niż jeden heks dalej. \n\nAby przypisać swoich pracowników do zbierania zasobów, twoja grupa musi być w trybie obozu {COLOR:yellow}" />
    <Entry Key="UI_TUTORIAL_CAMP4" Val="Ustawianie obozu" />
    <Entry Key="UI_TUTORIAL_CAMP5" Val="Aby założyć obóz: \n\n1. Kliknij lewym przyciskiem myszy grupę. Pojawi się menu radialne. \n\n2. Kliknij przycisk Obóz. \n\nEkran zbierania danych otworzy się automatycznie." />
    <Entry Key="UI_TUTORIAL_CAMP5A" Val="Aby założyć obóz:" />
    <Entry Key="UI_TUTORIAL_CAMP5B" Val="1. Kliknij lewym przyciskiem myszy grupę. Pojawi się menu radialne." />
    <Entry Key="UI_TUTORIAL_CAMP5C" Val="2. Kliknij przycisk Obóz." />
    <Entry Key="UI_TUTORIAL_CAMP5D" Val="Ekran Gathering otworzy się automatycznie." />
    <Entry Key="UI_TUTORIAL_CAMP6" Val="Kemping zwiększa również wskaźnik zdrowia, pod warunkiem, że grupa ma paliwo. Jedna jednostka paliwa ({ICON:FuelIcon}) jest zużywana na turę (więcej podczas zimy)." />
    <Entry Key="UI_TUTORIAL_CARDS1" Val="Właśnie rozpocząłeś grę w karty. \nKażda runda składa się z {COLOR:yellow}8 faz przygotowawczych {END_COLOR}i {COLOR:yellow}2 faz walki {END_COLOR}. \n\nAby wygrać, wyeliminuj wszystkie karty wroga." />
    <Entry Key="UI_TUTORIAL_CARDS2" Val="Podczas {COLOR:yellow}Faz przygotowawczych {END_COLOR}gracze na zmianę grają swoje karty." />
    <Entry Key="UI_TUTORIAL_CARDS2MORE" Val="Punkty akcji ({ICON:APIcon}) i opóźnienie ({ICON:DelayIcon}) są wyjaśnione nieco później. \n\nPodczas {COLOR:yellow}Faz Przygotowawczych {END_COLOR}wojownicy z każdej strony przygotowują się, ale nie walczą jeszcze z wrogiem. \n\nTo jest, gdy grasz w karty, wybierasz, których umiejętności użyć, rzucaj zaklęcia itp. \n\nKażdej decyzji podjętej podczas tury nie można zmienić po umieszczeniu karty na polu bitwy." />
    <Entry Key="UI_TUTORIAL_CARDS3" Val="{COLOR:green}Ally Turn {END_COLOR}" />
    <Entry Key="UI_TUTORIAL_CARDS3MORE" Val="- Karty można zagrać w różne czasy, ale za każdym razem, gdy zostaną zagrane, ich koszt rzucania wzrasta o 1 {ICON:APIcon}\n\n- Możesz zdecydować się na zapisanie swoich Punktów Akcji (AP) i użyć ich w następnej fazie przygotowania." />
    <Entry Key="UI_TUTORIAL_CARDS4" Val="{COLOR:red}Wroga kolej {END_COLOR}" />
    <Entry Key="UI_TUTORIAL_CARDS5" Val="Zasady gry {COLOR:yellow}na karcie {END_COLOR}: \n\n- Aby zagrać kartę, musisz zapłacić jej koszt rzucania ({ICON:APIcon}) \n\n- każda karta może mieć jedną lub więcej akcji (umiejętności) - Wybierz jedno." />
    <Entry Key="UI_TUTORIAL_CARDS6" Val="Gdy zabraknie Ci punktów akcji - kliknij {COLOR:yellow}Koniec {END_COLOR}. Otrzymasz więcej AP ({ICON:APIcon}) po tym, jak twój przeciwnik zakończy swoją turę." />
    <Entry Key="UI_TUTORIAL_CARDS7" Val="Po zakończeniu wszystkich faz przygotowawczych rozpoczynają się {COLOR:yellow}Fazy walki {END_COLOR}." />
    <Entry Key="UI_TUTORIAL_CARDS8" Val="{COLOR:yellow}Kolejka {END_COLOR}po prawej stronie ekranu pokazuje kolejność czynności. \n\nKarty o najniższym opóźnieniu {ICON:DelayIcon}są na górze i będą działać jako pierwsze." />
    <Entry Key="UI_TUTORIAL_CARDS9" Val="Szybkość działania karty zależy od wartości opóźnienia {ICON:DelayIcon}używanej umiejętności, a także od atrybutu Spryt {ICON:WitsIcon}." />
    <Entry Key="UI_TUTORIAL_CARDS10" Val="Wynik {COLOR:yellow}fazy walki {END_COLOR}zadecyduje, czy potrzebna jest kolejna runda. Wyzwanie będzie trwało tak długo, jak obaj gracze mają karty do gry w fazach przygotowania." />
    <Entry Key="UI_EQUIPMENT" Val="Sprzęt" />
    <Entry Key="UI_RECIPE" Val="Przepis" />
    <Entry Key="UI_TUTORIAL_EQUIP1" Val="{COLOR:yellow}Wyposażenie postaci {END_COLOR}bardzo wpływa na to, jak dobrze radzą sobie podczas wyzwania i jakie {COLOR:yellow}umiejętności {END_COLOR}mogą wykorzystać." />
    <Entry Key="UI_TUTORIAL_EQUIP2" Val="Umiejętności dostępne postaci można się nauczyć lub zdobyć na wyposażeniu. Skuteczność zależy od atrybutów postaci. \n\nNa przykład, jeśli umiejętność opiera się na Percepcji ({ICON:PerceptionIcon}), postać z wyższą Percepcją będzie skuteczniejsza dzięki tej umiejętności." />
    <Entry Key="UI_TUTORIAL_EQUIP3" Val="Możesz {COLOR:yellow}przypisać {END_COLOR}dowolne niewykorzystane przedmioty swoim ludziom, aby poprawić ich umiejętności. {COLOR:yellow}Przeciągnij i upuść element {END_COLOR}na postać, aby to zrobić." />
    <Entry Key="UI_TUTORIAL_EQUIP4" Val="Uważaj, aby nie przekroczyć limitu przenoszenia postaci ({ICON:CarryLimitIcon}). Jeśli zostaną obciążeni, zostaną ukarani." />
    <Entry Key="UI_TUTORIAL_GATHERING" Val="Ten ekran pokazuje Twoich ludzi po lewej i pobliskich zasobach po prawej. \n\nAby przypisać postać do zadania gromadzenia, przeciągnij i upuść je na wybrany zasób lub naciśnij zielony przycisk +. \n\nWykonanie zadania może zająć więcej niż jedną turę, w zależności od wartości umiejętności Gromadzenia postaci ({ICON:GatheringIcon})." />
    <Entry Key="UI_TUTORIAL_RECIPE1" Val="Ten ekran pozwala ci zdecydować, co chcesz stworzyć, i z czego chcesz to zrobić. \n\n{COLOR:yellow}Krok 1/5 {END_COLOR}- Wybierz przepis z listy na górze." />
    <Entry Key="UI_TUTORIAL_RECIPE2" Val="{COLOR:yellow}Krok 2/5 {END_COLOR}- Przeciągnij i upuść materiały z Inventory do {COLOR:yellow}Podstawowych i dodatkowych {END_COLOR}gniazd w Workbench. \n\nMateriały dostarczają esencji, która odblokowuje umiejętności. \n\nMożesz wybrać dowolny materiał, który odpowiada wymaganiom receptury. Potrzebny jest tylko jeden typ materiału w każdym wierszu." />
    <Entry Key="UI_TUTORIAL_RECIPE3" Val="Kompozyty to materiały, które mogą mieć więcej niż jeden typ. Na przykład Crystal Wood jest zarówno drewnem, jak i klejnotem." />
    <Entry Key="UI_TUTORIAL_RECIPE4" Val="{COLOR:yellow}Krok 3/5 {END_COLOR}- Wybierz umiejętność dla przedmiotu. \n\nNiektóre umiejętności wymagają określonego rodzaju esencji. Im więcej esencji dostarczą twoje materiały, tym silniejsza będzie umiejętność." />
    <Entry Key="UI_TUTORIAL_RECIPE5" Val="{COLOR:yellow}Krok 4/5 {END_COLOR}- Wyświetl podgląd przedmiotu. \n\nTo okno pokazuje szczegóły twojego przedmiotu. Możesz dodać ją do listy {COLOR:yellow}Ulubione {END_COLOR}, aby później łatwo ją odzyskać. Kliknij gwiazdkę, aby to zrobić." />
    <Entry Key="UI_TUTORIAL_RECIPE6" Val="{COLOR:yellow}Krok 5/5 {END_COLOR}- Naciśnij Potwierdź, aby dodać przepis do listy zadań rzemieślniczych. Pamiętaj, aby przypisać mieszkańców wioski do zadania!" />
    <Entry Key="UI_IMPORT" Val="Importuj tekst modułu" />
    <Entry Key="UI_EXPORT" Val="Eksportuj tekst modułu" />
    <Entry Key="UI_BUNDLE_MODE" Val="Tryb paczki" />
    <Entry Key="UI_SINGLE_MODE" Val="Tryb pojedynczy" />
    <Entry Key="UI_WHICH_FORM_OF_EXPORT" Val="{COLOR:#7b746e}Uwaga - narzędzia do importowania / eksportowania nie nadają się do kopiowania modułów, aby nadać je innym graczom, ponieważ pliki wyjściowe nie zawierają wszystkich danych zdarzeń, tylko tekst. {END_COLOR}\n\nWybierz, którą formę eksportu chcesz użyć: \n\n{COLOR:yellow}Tryb pakietu {END_COLOR}- wszystkie przełączane moduły są eksportowane jako jeden zestaw BundleBlock przygotowany do lokalizacji. \n\n{COLOR:yellow}Single Mode {END_COLOR}- eksportuje tylko aktualnie wybrany moduł, zachowując strukturę tekstu." />
    <Entry Key="UI_WHICH_FORM_OF_IMPORT" Val="{COLOR:#7b746e}Uwaga - narzędzia do importu / eksportu nie nadają się do kopiowania modułów, aby przekazać je innym graczom, ponieważ pliki wyjściowe nie zawierają wszystkich danych zdarzeń, tylko tekst. {END_COLOR}\n\nWybierz formę importu, której chcesz użyć: \n\n{COLOR:yellow}Tryb pakietu {END_COLOR}- importuj tekst z pliku BundleBlock. \n\n{COLOR:yellow}Single Mode {END_COLOR}- importuj tekst tylko dla aktualnie wybranego modułu." />
    <Entry Key="UI_SETTINGS" Val="Ustawienia" />
    <Entry Key="UI_MASTER_VOLUME" Val="Master Volume" />
    <Entry Key="UI_MUSIC_VOLUME" Val="Głośność muzyki" />
    <Entry Key="UI_SFX_VOLUME" Val="Wielkość SFX" />
    <Entry Key="UI_VOICEOVER_VOLUME" Val="Volume Volume" />
    <Entry Key="UI_COMBAT_ATTRIBUTES" Val="Atrybuty walki" />
    <Entry Key="UI_BONUS_LOSS" Val="Premia / strata:" />
    <Entry Key="UI_YOUR_OFFER" Val="Twoja oferta" />
    <Entry Key="UI_THEIR_OFFER" Val="Ich oferta" />
    <Entry Key="UI_VALUE" Val="Wartość" />
    <Entry Key="UI_NONAME" Val="Pusty" />
    <Entry Key="UI_TRADE_INVITATION" Val="Zaproszenie do handlu" />
    <Entry Key="UI_TRADE_INVITATION1" Val="{COLOR:yellow}{0}{END_COLOR}chce handlować z tobą. Zaakceptować żądanie handlowe?" />
    <Entry Key="UI_TRADE_INVITATION2" Val="Oczekiwanie, aż inny gracz zaakceptuje żądanie handlu ..." />
    <Entry Key="UI_YES" Val="Tak" />
    <Entry Key="UI_NO" Val="Nie" />
    <Entry Key="UI_FOOD" Val="Żywność" />
    <Entry Key="UI_MATERIALS" Val="Materiały" />
    <Entry Key="UI_TRADE_ALLOWED" Val="Dozwolony handel" />
    <Entry Key="UI_TRADE_NOT_ALLOWED" Val="Handel niedozwolony" />
    <Entry Key="UI_CURRENT_BALANCE" Val="Aktualne saldo" />
    <Entry Key="UI_GOD_POINTS_AND_TRAITS" Val="Punkty Boga i cechy" />
    <Entry Key="UI_TUTORIAL_GOD_POINTS1" Val="Ten ekran umożliwia dostosowanie cech twojego bóstwa. \n\nKażda karta reprezentuje jedną cechę. \n\nMożesz mieszać i dopasowywać cechy z kategorii {COLOR:yellow}Characters {END_COLOR}i {COLOR:yellow}Bonusy {END_COLOR}." />
    <Entry Key="UI_TUTORIAL_GOD_POINTS2" Val="Aby przypisać cechę, {COLOR:yellow}przeciągnij ją {END_COLOR}z listy cech {COLOR:yellow}i upuść {END_COLOR}na pasującą szczelinę. \n\nCałkowity koszt cech jest ograniczony i zależy od ustawienia trudności." />
    <Entry Key="UI_TUTORIAL_GOD_POINTS3A" Val="Każdy bóg ma swoją unikalną cechę i specjalizuje się w innym zestawie {COLOR:yellow}domen {END_COLOR}." />
    <Entry Key="UI_TUTORIAL_GOD_POINTS3B" Val="Możesz wybrać tylko cechy, które pasują do tych konkretnych domen." />
    <Entry Key="UI_TUTORIAL_GOD_POINTS4" Val="Nowe cechy można odblokować za pomocą {COLOR:yellow}punktów Boga {END_COLOR}- są one przyznawane po zakończeniu gry. Po odblokowaniu cecha staje się dostępna dla każdej gry." />
    <Entry Key="UI_TUTORIAL_GOD_POINTS5" Val="Cechy są opcjonalne, możesz dowolnie rozpocząć grę bez nich, jeśli chcesz." />
    <Entry Key="UI_MY_GROUP" Val="Moja grupa" />
    <Entry Key="UI_MY_OFFER" Val="Moja oferta" />
    <Entry Key="UI_OTHER_GROUP" Val="Inna grupa" />
    <Entry Key="UI_DEV_ADD_RP" Val="Dodaj punkty awansu" />
    <Entry Key="UI_DEV_ADD_RESOURCES" Val="Dodaj zasoby" />
    <Entry Key="UI_OPTIONAL_EVENT_INVITE_GLOBAL" Val="{COLOR:yellow}{0}{END_COLOR}zaprosił Cię na wydarzenie. Chcesz dołączyć?" />
    <Entry Key="UI_MANDATORY_EVENT_INVITE_GLOBAL" Val="{COLOR:yellow}{0}{END_COLOR}wymaga twojej pomocy przy wydarzeniu. Odmowa nie wchodzi w grę." />
    <Entry Key="UI_START_EVENT" Val="Rozpocznij zdarzenie" />
    <Entry Key="UI_TUTORIAL_LEVEL_UP1" Val="Poziom wyżej" />
    <Entry Key="UI_TUTORIAL_LEVEL_UP2" Val="Jedna z twoich postaci zdobyła wystarczające doświadczenie, by {COLOR:yellow}podnieść poziom. {END_COLOR}\n\n{COLOR:yellow}Kliknij ikonę postaci w obszarze powiadomień, aby poprawić ich umiejętności. {END_COLOR}" />
    <Entry Key="UI_TUTORIAL_LEVEL_UP3" Val="Poziomy na przemian między bonusami do statystyk i umiejętności postaci. \n\nWybierz żądany atrybut dla każdego znaku i naciśnij Potwierdź. \n\nNie będziesz w stanie wycofać swoich wyborów." />
    <Entry Key="UI_MORALE_BONUSES" Val="Morale - bonusy" />
    <Entry Key="UI_CURRENT_MORALE" Val="Aktualne morale" />
    <Entry Key="UI_MORALE_BONUS0" Val="Brak" />
    <Entry Key="UI_MORALE_BONUS1" Val="+1 ekranowanie ({ICON:ShieldingIcon})" />
    <Entry Key="UI_MORALE_BONUS2" Val="+ 10% punktów życia ({ICON:HealthPhysicalIcon}{ICON:HealthMentalIcon}{ICON:HealthSpiritualIcon})" />
    <Entry Key="UI_MORALE_BONUS3" Val="+ 10% efektywności zadania \n+ 1 ekranowanie ({ICON:ShieldingIcon})" />
    <Entry Key="UI_MORALE_BONUS4" Val="+1 regeneracji zdrowia ({ICON:PhysicalRegenerationIcon})" />
    <Entry Key="UI_MORALE_BONUS5" Val="+1 MP ({ICON:MPIcon})" />
    <Entry Key="UI_MORALE_BONUS6" Val="+ 10% obrażeń ({ICON:ChallengePMS})" />
    <Entry Key="UI_MORALE_BONUS7" Val="+ 10% punktów wytrzymałości ({ICON:HealthPhysicalIcon}{ICON:HealthMentalIcon}{ICON:HealthSpiritualIcon}) \n+ 1 regeneracja ({ICON:PhysicalRegenerationIcon}{ICON:MentalRegenerationIcon}{ICON:SpiritualRegenerationIcon})" />
    <Entry Key="UI_MORALE_BONUS8" Val="+ 10% efektywności zadania" />
    <Entry Key="UI_MORALE_BONUS9" Val="Zakres widoku +1 ({ICON:ViewRangeIcon})" />
    <Entry Key="UI_MORALE_BONUS10" Val="+1 MP ({ICON:MPIcon})" />
    <Entry Key="UI_LOGBOOK" Val="Dziennik" />
    <Entry Key="UI_END_OF_QUEST" Val="Koniec zadania" />
    <Entry Key="UI_RECYCLE" Val="Recykling" />
    <Entry Key="UI_RECYCLE_ALL" Val="Recycle All" />
    <Entry Key="UI_TUTORIALS" Val="Samouczki" />
    <Entry Key="UI_TUTORIAL1" Val="Samouczek 1" />
    <Entry Key="UI_TUTORIAL2" Val="Samouczek 2" />
    <Entry Key="UI_TUTORIAL3" Val="Samouczek 3" />
    <Entry Key="UI_NO_SAVE_FILES_FOUND" Val="Nie znaleziono plików składowania." />
    <Entry Key="UI_MUHA_PHOTON_CLOUD" Val="MuHa Photon Cloud" />
    <Entry Key="UI_SELF_HOSTED_SERVER" Val="Self Hosted Server" />
    <Entry Key="UI_CHANGE_PROFILE" Val="Zmień profil" />
    <Entry Key="UI_GAMEPLAY" Val="Rozgrywka" />
    <Entry Key="UI_AUDIO" Val="Audio" />
    <Entry Key="UI_VIDEO" Val="Wideo" />
    <Entry Key="UI_ALWAYS_CONFIRM_DISMANTLE" Val="Zawsze potwierdzaj demontaż" />
    <Entry Key="UI_FOOD_ALERT_THRESHOLD" Val="Próg alarmu żywnościowego" />
    <Entry Key="UI_FUEL_ALERT_THRESHOLD" Val="Próg alarmu paliwa" />
    <Entry Key="UI_HP_ALERT_THRESHOLD" Val="Próg alarmowy punktów wytrzymałości" />
    <Entry Key="UI_PLAY_INTRO" Val="Zagraj w Intro" />
    <Entry Key="UI_AUTO_END_TURN_CHALL" Val="Obrót automatyczny podczas wyzwań" />
    <Entry Key="UI_ALLOW_ENTERING_WATER_TILES" Val="Pozwól wchodzić do płytek wodnych" />
    <Entry Key="UI_RESET_HELP" Val="Zresetuj pomoc" />
    <Entry Key="UI_LANGUAGE" Val="Język:" />
    <Entry Key="UI_AMBIENT_OCCLUSION" Val="Okluzja otoczenia" />
    <Entry Key="UI_ANTI_ALIASING" Val="Wygładzanie" />
    <Entry Key="UI_SUPER_SAMPLING" Val="Super próbkowanie" />
    <Entry Key="UI_VSYNC" Val="VSync:" />
    <Entry Key="UI_OFF" Val="Wył" />
    <Entry Key="UI_LIMIT_FPS" Val="Ogranicz FPS" />
    <Entry Key="UI_NODE_USABLE_ONLY_ONCE" Val="Węzeł używany tylko raz" />
    <Entry Key="UI_EVENT_USABLE_ONLY_ONCE" Val="Zdarzenie możliwe tylko raz" />
    <Entry Key="UI_F8_REPORT" Val="Naciśnij klawisz F8, aby zgłosić błąd" />
    <Entry Key="UI_SAVE_SUCCESSFUL" Val="Twoja gra została zapisana." />
    <Entry Key="UI_ROOM_NAME_ALREADY_IN_USE" Val="Nazwa pokoju jest już w użyciu." />
    <Entry Key="UI_SET_SAVE_NAME" Val="Wpisz nazwę zapisu:" />
    <Entry Key="UI_SEA_EVENT" Val="Wydarzenie morskie" />
    <Entry Key="UI_BIOME" Val="Biome:" />
    <Entry Key="UI_FEMALE" Val="Kobieta" />
    <Entry Key="UI_MALE" Val="Mężczyzna" />
    <Entry Key="UI_FUEL_FILTER" Val="Paliwo" />
    <Entry Key="UI_COOKED_FOOD_FILTER" Val="Gotowane jedzenie" />
    <Entry Key="UI_RAW_FOOD_FILTER" Val="Surowe jedzenie" />
    <Entry Key="UI_TOOLS_FILTER" Val="Narzędzia" />
    <Entry Key="UI_JEWELLERY_FILTER" Val="Biżuteria" />
    <Entry Key="UI_PETS_FILTER" Val="Zwierzęta" />
    <Entry Key="UI_GAME_SUMMARY" Val="Podsumowanie gry" />
    <Entry Key="UI_ENTER_CHARACTER_NAME" Val="Wpisz nazwę postaci" />
    <Entry Key="UI_ROOM_DOES_NOT_EXIST" Val="Ten pokój nie istnieje." />
    <Entry Key="UI_KEEP_PLAYING" Val="Graj dalej" />
    <Entry Key="UI_END_GAME" Val="Zakończ grę" />
    <Entry Key="UI_VIEW_STATS" Val="Wyświetl statystyki" />
    <Entry Key="UI_FINISHING_MAIN_QUEST" Val="Wykończenie głównego zadania:" />
    <Entry Key="UI_MAP_TILES_REVEALED" Val="Ujawniono kafelki mapy:" />
    <Entry Key="UI_XP_COLLECTED" Val="Zebrane punkty doświadczenia:" />
    <Entry Key="UI_AP_COLLECTED" Val="Zebrane punkty awansu:" />
    <Entry Key="UI_TURNS_SURVIVED" Val="Przetrwały zwroty:" />
    <Entry Key="UI_BEST_ITEM" Val="Najlepszy przedmiot:" />
    <Entry Key="UI_MOST_POWERFUL_CHARACTER" Val="Najmocniejsza postać:" />
    <Entry Key="UI_EVENTS_TAKEN_PART_IN" Val="Event Paths Uncovered:" />
    <Entry Key="UI_TOTAL_POINTS" Val="PUNKTY CAŁKOWITE:" />
    <Entry Key="UI_GAME_DIFFICULTY_ADJUSTMENT" Val="Dostosowanie trudności gry:" />
    <Entry Key="UI_GOD_POINTS_AWARDED" Val="Przyznano punkty God:" />
    <Entry Key="UI_TUTORIAL_GODS_CHOSEN1" Val="Tutaj możesz zdecydować, kto będzie Bożym Wybranym. Ta postać będzie ważna dla linii zadań." />
    <Entry Key="UI_TUTORIAL_GODS_CHOSEN2" Val="Wybrani mogą należeć do każdej klasy, od której zaczynasz, włącznie z dowolnymi dodatkowymi postaciami, które mógłbyś wybrać z Cech Boga." />
    <Entry Key="UI_TUTORIAL_GODS_CHOSEN3" Val="Nie zapomnij podać imion!" />
    <Entry Key="UI_CREDITS" Val="Kredyty" />
    <Entry Key="UI_DATABASE" Val="Baza danych" />
    <Entry Key="UI_SETTLE" Val="Osadź" />
    <Entry Key="UI_TUTORIAL_SETTLE1" Val="Jeśli chcesz osiedlić się i zbudować wioskę, najpierw ustaw Obóz, a następnie otwórz ekran Craftingu i utwórz Idola." />
    <Entry Key="UI_TUTORIAL_SETTLE2" Val="Budowanie Idola wymaga rzadkiego materiału zwanego Kosmicznym Nasieniem." />
    <Entry Key="UI_TUTORIAL_SETTLE3" Val="Otrzymałeś jeden od Theodore'a na początku, ale używaj go mądrze - kiedy twoja wioska zostanie zbudowana, nie możesz jej po prostu zburzyć, aby przenieść się gdzie indziej!" />
    <Entry Key="UI_TUTORIAL_SETTLE4" Val="Premie przyznawane przez Idola zależą od materiałów użytych do jego budowy. \n\nGdy Idol będzie gotowy, będziesz mógł zbudować inne budynki, pod warunkiem, że najpierw je zbadałeś." />
    <Entry Key="UI_DEV_OPTIONS" Val="Opcje Dev" />
    <Entry Key="UI_WARNING2" Val="OSTRZEŻENIE!" />
    <Entry Key="UI_DEV_OPTIONS_WARNING1" Val="Zmiana tych opcji może doprowadzić do awarii. Przeczytaj podpowiedzi, aby uzyskać dodatkowe informacje." />
    <Entry Key="UI_DEV_OPTIONS_WARNING2" Val="Zmiana plików gry może przerwać grę lub spowodować niezamierzone zachowanie. Deweloper nie będzie w stanie zapewnić obsługi gry zmodulowanej." />
    <Entry Key="UI_FORCE_OLD_CACHE" Val="Wymuś ładowanie pamięci podręcznej" />
    <Entry Key="UI_ENABLE_DEV_CONSOLE" Val="Włącz konsolę Dev" />
    <Entry Key="UI_WELCOME_HEADING" Val="Thea 2 - Wczesny dostęp" />
    <Entry Key="UI_WELCOME_MESSAGE1" Val="Pamiętaj, że gra nie jest uważana za ukończoną. Na tym etapie należy spodziewać się błędów i brakujących funkcji." />
    <Entry Key="UI_WELCOME_MESSAGE2" Val="Jeśli znalazłeś błąd i chciałbyś go zgłosić - naciśnij F8." />
    <Entry Key="UI_WELCOME_MESSAGE3" Val="Pamiętaj, że zapisy mogą nie być zgodne między łatami." />
    <Entry Key="UI_LETS_PLAY" Val="Zagrajmy!" />
    <Entry Key="UI_TUTORIAL_CHALLENGE1_HEADING1" Val="Samouczek wyzwania - 1/8" />
    <Entry Key="UI_TUTORIAL_CHALLENGE1_HEADING2" Val="Samouczek wyzwania - 2/8" />
    <Entry Key="UI_TUTORIAL_CHALLENGE1_HEADING3" Val="Samouczek wyzwania - 3/8" />
    <Entry Key="UI_TUTORIAL_CHALLENGE1_HEADING4" Val="Samouczek wyzwania - 4/8" />
    <Entry Key="UI_TUTORIAL_CHALLENGE1_HEADING5" Val="Samouczek wyzwania - 5/8" />
    <Entry Key="UI_TUTORIAL_CHALLENGE1_HEADING6" Val="Samouczek wyzwania - 6/8" />
    <Entry Key="UI_TUTORIAL_CHALLENGE1_HEADING7" Val="Samouczek wyzwania - 7/8" />
    <Entry Key="UI_TUTORIAL_CHALLENGE1_HEADING8" Val="Samouczek wyzwania - 8/8" />
    <Entry Key="UI_TUTORIAL_CHALLENGE1_1" Val="Witamy w pierwszym wyzwaniu!" />
    <Entry Key="UI_TUTORIAL_CHALLENGE1_2" Val="Nauczmy cię podstaw, więc wiesz, co się dzieje." />
    <Entry Key="UI_TUTORIAL_CHALLENGE1_3" Val="Ekran wyzwania składa się z:" />
    <Entry Key="UI_TUTORIAL_CHALLENGE1_4" Val="- {COLOR:yellow}Hand {END_COLOR}- to są twoje karty," />
    <Entry Key="UI_TUTORIAL_CHALLENGE1_5" Val="- {COLOR:yellow}Pole bitwy {END_COLOR}- gdzie ty i twój przeciwnik umieszczacie karty, które chcecie zagrać," />
    <Entry Key="UI_TUTORIAL_CHALLENGE1_6" Val="- {COLOR:yellow}Pasek sekwencji {END_COLOR}- pokazuje kolejność działań," />
    <Entry Key="UI_TUTORIAL_CHALLENGE1_7" Val="- {COLOR:yellow}Wskaźniki skrętu {END_COLOR}- status bieżącej rundy." />
    <Entry Key="UI_TUTORIAL_CHALLENGE1_8" Val="Ty i twój przeciwnik na zmianę zagrywacie swoje karty podczas {COLOR:yellow}Przygotowań Turns. {END_COLOR}" />
    <Entry Key="UI_TUTORIAL_CHALLENGE1_9" Val="Twoje zwroty" />
    <Entry Key="UI_TUTORIAL_CHALLENGE1_10" Val="Enemy Turns" />
    <Entry Key="UI_TUTORIAL_CHALLENGE1_11" Val="Wszystkie akcje są umieszczane w kolejce (Pasek Sekwencji pokazuje rozkaz) i wykonywane później, w Fight Turns." />
    <Entry Key="UI_TUTORIAL_CHALLENGE1_12" Val="Rozegranie karty po raz pierwszy kosztuje 1 punkt akcji ({ICON:APIcon})." />
    <Entry Key="UI_TUTORIAL_CHALLENGE1_13" Val="{COLOR:yellow}Aby zagrać kartę: {END_COLOR}" />
    <Entry Key="UI_TUTORIAL_CHALLENGE1_14" Val="1. Kliknij kartę na dłoni. \n2. Wybierz akcję. \n3. Kliknij gniazdo na polu bitwy." />
    <Entry Key="UI_SHOW_ME" Val="Pokaż mi" />
    <Entry Key="UI_TUTORIAL_CHALLENGE1_15" Val="Kiedy wydajesz AP ({ICON:APIcon}), kończ swoją turę, a wróg będzie miał szansę wykonać swoje działania." />
    <Entry Key="UI_TUTORIAL_CHALLENGE1_16" Val="Każdy z was będzie miał {COLOR:yellow}4 tury przygotowania {END_COLOR}i dostaniecie AP ({ICON:APIcon}) na początku każdej tury." />
    <Entry Key="UI_TUTORIAL_CHALLENGE1_17" Val="Możesz zagrać tę samą postać więcej niż raz." />
    <Entry Key="UI_TUTORIAL_CHALLENGE1_18" Val="Za każdym razem, gdy grasz tę samą postać, jej koszt AP wzrasta o {ICON:APIcon}1." />
    <Entry Key="UI_TUTORIAL_CHALLENGE1_19" Val="Zobaczysz ikonę {COLOR:yellow}Klon {END_COLOR}na każdej karcie, która została zagrana więcej niż raz." />
    <Entry Key="UI_TUTORIAL_CHALLENGE1_20" Val="Jego kolor będzie inny, jeśli sklonowane jednostki są różne." />
    <Entry Key="UI_TUTORIAL_CHALLENGE1_21" Val="Każda akcja, która atakuje jednego z Klonów, będzie miała wpływ na wszystkie." />
    <Entry Key="UI_TUTORIAL_CHALLENGE1_22" Val="Kiedy przygotowania się kończą, {COLOR:yellow}rozpoczynają się walki {END_COLOR}." />
    <Entry Key="UI_TUTORIAL_CHALLENGE1_23" Val="Postacie wymienią ciosy i wykonają akcje zgodnie z rozkazem na pasku sekwencji {COLOR:yellow}." />
    <Entry Key="UI_TUTORIAL_CHALLENGE1_24" Val="Akcje z najniższym opóźnieniem {COLOR:yellow}({END_COLOR}) będą wykonywane jako pierwsze." />
    <Entry Key="UI_TUTORIAL_CHALLENGE1_25" Val="Jeśli po pierwszej rundzie nie ma zwycięzcy, rozpocznie się kolejna runda." />
    <Entry Key="UI_TUTORIAL_CHALLENGE1_26" Val="Wyzwanie będzie trwać, dopóki ani ty, ani twój wróg nie stracicie wszystkich swoich postaci." />
    <Entry Key="UI_TURN_INDICATORS" Val="Wskaźniki skrętu" />
    <Entry Key="UI_SEQUENCE_BAR" Val="Pasek sekwencji" />
    <Entry Key="UI_YOUR_HAND" Val="Twoja ręka" />
    <Entry Key="UI_BATTLEFIELD_ALLIES" Val="Battlefield - Allies" />
    <Entry Key="UI_BATTLEFIELD_ENEMIES" Val="Pole bitwy - wrogowie" />
    <Entry Key="UI_PREPARATION_TURNS" Val="Przygotowanie do skrętu" />
    <Entry Key="UI_FIGHT_TURNS" Val="Fight Turns" />
    <Entry Key="UI_TUTORIAL_CHALLENGE2_HEADING1" Val="Samouczek wyzwania - 1/3" />
    <Entry Key="UI_TUTORIAL_CHALLENGE2_HEADING2" Val="Samouczek wyzwania - 2/3" />
    <Entry Key="UI_TUTORIAL_CHALLENGE2_HEADING3" Val="Samouczek wyzwania - 3/3" />
    <Entry Key="UI_TUTORIAL_CHALLENGE2_1" Val="Kliknij środkowy przycisk myszy (lub użyj kółka przewijania), aby powiększyć kartę, jeśli chcesz zobaczyć dodatkowe informacje na jej temat." />
    <Entry Key="UI_TUTORIAL_CHALLENGE2_2" Val="To wyzwanie jest znacznie trudniejsze - twój Wojownik tak naprawdę nie specjalizuje się w wyzwaniach duchowych." />
    <Entry Key="UI_TUTORIAL_CHALLENGE2_3" Val="W przypadku, gdy zwycięstwo nie jest prawdopodobne, dobrym pomysłem może być ucieczka." />
    <Entry Key="UI_TUTORIAL_CHALLENGE2_4" Val="Kliknij przycisk {COLOR:yellow}Forfeit Challenge {END_COLOR}i potwierdź swoją decyzję w wyskakującym okienku." />
    <Entry Key="UI_TUTORIAL_CHALLENGE2_5" Val="Twój wojownik może doznać pewnych obrażeń i / lub opowieść zareaguje na twoje działanie, ale czasami lepiej jest biec i żyć niż walczyć i umierać." />
    <Entry Key="UI_TUTORIAL_CHALLENGE3_HEADING1" Val="Samouczek wyzwania - 1/4" />
    <Entry Key="UI_TUTORIAL_CHALLENGE3_HEADING2" Val="Samouczek wyzwania - 2/4" />
    <Entry Key="UI_TUTORIAL_CHALLENGE3_HEADING3" Val="Samouczek wyzwania - 3/4" />
    <Entry Key="UI_TUTORIAL_CHALLENGE3_HEADING4" Val="Samouczek wyzwania - 4/4" />
    <Entry Key="UI_TUTORIAL_CHALLENGE3_1" Val="To jest {COLOR:yellow}Wyzwanie vs Koncepcja {END_COLOR}. W wyzwaniach vs koncepcja nie możesz używać umiejętności pochodzących z wyposażonych przedmiotów. Innymi słowy - liczą się tylko twoje naturalne zdolności." />
    <Entry Key="UI_TUTORIAL_CHALLENGE3_2" Val="Jeśli twoje postacie nie mają odpowiedniej umiejętności, której można użyć w wyzwaniu, w którym się znajdują, będą mogły użyć domyślnego ataku, ale nie jest to zbyt skuteczne." />
    <Entry Key="UI_TUTORIAL_CHALLENGE3_3" Val="Utrata (lub utrata) wyzwania przeciwko koncepcji może również mieć złe konsekwencje, ale zazwyczaj nie wpływa na punkty życia twoich postaci." />
    <Entry Key="UI_TUTORIAL_CHALLENGE3_4" Val="Przy okazji - podczas Fight Turns w tym miejscu pojawi się suwak Animation Speed." />
    <Entry Key="UI_TUTORIAL_CHALLENGE3_5" Val="Pozwala zmienić szybkość gry w walce i ataku." />
    <Entry Key="UI_TUTORIAL_CHALLENGE4_1" Val="W tej walce twoje postacie mają do dyspozycji pewne przedmioty." />
    <Entry Key="UI_TUTORIAL_CHALLENGE4_2" Val="Przedmioty mają różne umiejętności, a ich prawidłowe użycie zwiększa szansę na wygraną." />
    <Entry Key="UI_TUTORIAL_CHALLENGE4_3" Val="Umiejętności mogą mieć różne reguły użytkowania, które określają, co mogą celować, kiedy ich efekty są wyzwalane i jaki efekt jest stosowany w momencie ich uruchomienia." />
    <Entry Key="UI_TUTORIAL_CHALLENGE4_4" Val="Decydując się na umiejętność, której chcesz użyć, ustaw kursor nad każdą ikoną, aby zobaczyć, jak działa umiejętność." />
    <Entry Key="UI_TUTORIAL_CHALLENGE4_5" Val="Na przykład - {COLOR:yellow}Różdżka {END_COLOR}trzymana przez {COLOR:yellow}Anya {END_COLOR}jest bronią dystansową {COLOR:yellow}. Możesz go używać tylko z {END_COLOR}ranged row {COLOR:yellow}." />
    <Entry Key="UI_TUTORIAL_CHALLENGE4_6" Val="Broń dystansowa może atakować dowolną postać wroga, chyba że stoi w rzędzie walczącym przed swoim użytkownikiem, blokując jej widok." />
    <Entry Key="UI_TUTORIAL_CHALLENGE4_7" Val="Będziesz mógł wybrać cel podczas Fight Turns. Jednakże, jeśli Anya zostanie zablokowana przez wroga, ten wróg musi być atakowany." />
    <Entry Key="UI_TUTORIAL_CHALLENGE4_8" Val="{COLOR:yellow}Kamil {END_COLOR}trzyma zwój z {COLOR:yellow}umiejętnością Lullabye {END_COLOR}. Użycie go {COLOR:yellow}natychmiast {END_COLOR}zwiększy opóźnienie ({ICON:DelayIcon}) wrogiej postaci na polu bitwy, powodując, że będą działać później niż normalnie." />
    <Entry Key="UI_TUTORIAL_CHALLENGE4_9" Val="W przeciwieństwie do ataków bronią, natychmiastowe umiejętności stosują swój efekt, gdy potwierdzasz cel (y)." />
    <Entry Key="UI_TUTORIAL_CHALLENGE5_HEADING1" Val="Samouczek wyzwania - 1/5" />
    <Entry Key="UI_TUTORIAL_CHALLENGE5_HEADING2" Val="Samouczek wyzwania - 2/5" />
    <Entry Key="UI_TUTORIAL_CHALLENGE5_HEADING3" Val="Samouczek wyzwania - 3/5" />
    <Entry Key="UI_TUTORIAL_CHALLENGE5_HEADING4" Val="Samouczek wyzwania - 4/5" />
    <Entry Key="UI_TUTORIAL_CHALLENGE5_HEADING5" Val="Samouczek wyzwania - 5/5" />
    <Entry Key="UI_TUTORIAL_CHALLENGE5_1" Val="Ojej, ci bandyci nie mają szans przeciwko czystej wspaniałości twoich krasnoludów." />
    <Entry Key="UI_TUTORIAL_CHALLENGE5_2" Val="Wykorzystajmy tę walkę jako okazję do objaśnienia Obrażeń Osłony, Prawdziwego i Splash." />
    <Entry Key="UI_TUTORIAL_CHALLENGE5_3" Val="{COLOR:yellow}Shielding {END_COLOR}chroni punkty wytrzymałości twoich postaci i zazwyczaj jest najpierw usuwany. Jest uzupełniany między wyzwaniami, ale nie między rundami." />
    <Entry Key="UI_TUTORIAL_CHALLENGE5_4" Val="Jeden z twoich krasnoludów nosi {COLOR:yellow}tarczę {END_COLOR}, która pozwala mu chronić innego sojusznika, zwiększając jego osłonę." />
    <Entry Key="UI_TUTORIAL_CHALLENGE5_5" Val="Nosi także Topór, który zadaje ulepszoną wersję {COLOR:yellow}Prawdziwych Obrażeń {END_COLOR}({ICON:DamageTrueAncient}). Twój krasnolud nie tylko zadaje pełne obrażenia punktom trafienia, ale także zadaje tyle samo obrażeń osłonom wroga." />
    <Entry Key="UI_TUTORIAL_CHALLENGE5_6" Val="Twój drugi krasnolud jest wyposażony w młotek. Jest to powolna, ale raczej potężna broń, która wykonuje {COLOR:yellow}Splash Damage {END_COLOR}({ICON:DamageTSplash}). Zada obrażenia wrogom, którzy stoją obok głównego celu twojej postaci." />
    <Entry Key="UI_TUTORIAL_CHALLENGE5_7" Val="Umieść kursor myszy nad postacią na polu bitwy, aby zobaczyć ich cel (y)." />
    <Entry Key="UI_TUTORIAL_CHALLENGE5_8" Val="Jeśli {COLOR:yellow}Klony {END_COLOR}stoją obok siebie, wszystkie zostaną dotknięte pluśnięciem i otrzymają o wiele więcej obrażeń." />
    <Entry Key="UI_TUTORIAL_CHALLENGE5_9" Val="Spróbuj wykorzystać ten fakt, grając umiejętnością obrażeń od rozbryzgów i uważaj, jak umieszczasz swoje jednostki, jeśli podejrzewasz, że wróg może mieć broń obrażeń od rozbryzgów." />
    <Entry Key="UI_DB_VER" Val="Wersja bazy danych:" />
    <Entry Key="UI_CURRENT" Val="Bieżący" />
    <Entry Key="UI_THIS_CHANGE_REQUIRES_RESTART" Val="Ta zmiana zostanie zastosowana po ponownym uruchomieniu aplikacji." />
    <Entry Key="UI_CURENT_DB_NO_CHANGE_NEEDED" Val="Baza danych nie została zmieniona, ponowne uruchomienie nie jest wymagane." />
    <Entry Key="UI_SAVE_INCOMPATIBLE" Val="Oszczędność, którą próbujesz załadować, jest niezgodna z aktualnie używaną bazą danych gier. Zalecamy przejście na pasującą wersję gry przy użyciu gałęzi beta." />
    <Entry Key="UI_DEFAULT" Val="Domyślna baza danych" />
    <Entry Key="UI_CONFIRM_DB_DELETE" Val="Czy na pewno chcesz usunąć tę bazę danych?" />
    <Entry Key="UI_CONFIRM_DB_SWITCH" Val="Czy na pewno chcesz przełączyć się do tej bazy danych?" />
    <Entry Key="UI_VIEW_SUMMARY" Val="Wyświetl podsumowanie" />
    <Entry Key="UI_DEV_TOXINE_GROUP" Val="Zastosuj Toxine do grupy" />
    <Entry Key="UI_DEV_COMBO_ADD" Val="Dodaj ładunek towaru" />
    <Entry Key="UI_DEV_EXPORT_GROUP_POWERS" Val="Eksportuj moce grupy" />
    <Entry Key="UI_DEV_LOG_SELECTED_GROUP_DEBUG" Val="Log Selected Group Debug" />
    <Entry Key="UI_DEV_ADD_MP" Val="Dodaj MP" />
    <Entry Key="UI_DEV_ADD_XP" Val="Dodaj XP" />
    <Entry Key="UI_CLIENT_CONNECTION_LOST" Val="Straciłeś połączenie z serwerem." />
    <Entry Key="UI_YOU_HAVE_BEEN_DISCONNECTED" Val="Zostałeś odłączony." />
    <Entry Key="UI_MASTER_LEFT_THE_GAME" Val="Serwer opuścił grę." />
    <Entry Key="UI_RESOLVE_MANUALLY" Val="Rozwiąż ręcznie" />
    <Entry Key="UI_ACCEPT_OUTCOME" Val="Akceptuj wynik" />
    <Entry Key="UI_AUTORESOLVE_OUTCOME" Val="Wynik Autoresolve" />
    <Entry Key="UI_TOTAL_DEFEAT" Val="Całkowita porażka" />
    <Entry Key="UI_VICTORY_WITH_GRAVE_INJURIES" Val="Zwycięstwo z ciężkimi obrażeniami" />
    <Entry Key="UI_VICTORY_WITH_SERIOUS_INJURIES" Val="Zwycięstwo z poważnymi obrażeniami" />
    <Entry Key="UI_VICTORY_WITH_INJURIES" Val="Zwycięstwo z obrażeniami" />
    <Entry Key="UI_PERFECT_VICTORY" Val="Doskonałe zwycięstwo" />
    <Entry Key="UI_AUTORESOLVE_OUTCOME_INFO" Val="Czy akceptujesz ten wynik lub chcesz spróbować rozwiązać to wyzwanie ręcznie?" />
    <Entry Key="UI_GROUP_INFO" Val="Informacje o grupie" />
    <Entry Key="UI_TUTORIAL_GROUP_INFO1" Val="Ten ekran umożliwia zarządzanie zużyciem żywności i paliwa w grupie." />
    <Entry Key="UI_TUTORIAL_GROUP_INFO2" Val="Możesz ograniczyć określone rodzaje lub nawet nie dopuścić do zbierania nowych produktów żywnościowych lub paliwowych." />
    <Entry Key="UI_TUTORIAL_GROUP_INFO3" Val="Pamiętaj, że im więcej rodzajów żywności twoi ludzie mogą używać, tym lepsze jest ich morale." />
    <Entry Key="UI_TUTORIAL_GROUP_INFO4" Val="Wysokie morale zapewnia lepsze bonusy. Służy również do uzupełnienia Mentalnych Punktów Uderzenia - Poczytalności ({ICON:HealthMentalIcon})." />
    <Entry Key="UI_TUTORIAL_GROUP_INFO5" Val="Panel bonusów morale pokazuje morale wszystkich postaci w tej grupie na pierwszy rzut oka." />
    <Entry Key="UI_EMPTY" Val="" />
    <Entry Key="UI_SELECT_AN_EVENT" Val="Wybierz wydarzenie" />
    <Entry Key="UI_OBSOLETE_PROFILE_PLEASE_CHANGE" Val="Profile utworzone przy użyciu demo September Backer są przestarzałe. Usuń je i utwórz nowy profil." />
    <Entry Key="UI_STATUS" Val="Status" />
    <Entry Key="UI_MODULES_HASH" Val="Hash modułów:" />
    <Entry Key="UI_LOAD_ANYWAY" Val="Załaduj mimo wszystko" />
    <Entry Key="UI_AUTOSAVE" Val="Autozapis" />
    <Entry Key="UI_GOD_POINTS_UPDATE" Val="Punkty Boga profilu są aktualizowane za każdym razem, gdy otwierany jest ekran Podsumowanie." />
    <Entry Key="UI_30" Val="30 FPS" />
    <Entry Key="UI_60" Val="60 FPS" />
    <Entry Key="UI_VSYNC_1" Val="VSync każdej ramki" />
    <Entry Key="UI_VSYNC_2" Val="VSync co druga ramka" />
    <Entry Key="UI_ISSUE_ENCOUNTERED" Val="Wystąpił problem" />
    <Entry Key="UI_ISSUE_ENCOUNTERED_DES" Val="Wystąpił problem. Gra może być niestabilna i / lub ulec awarii. Wszelkie zapisy utworzone po tym punkcie mogą być uszkodzone. \n\nZamknij to okienko i naciśnij klawisz F8, aby zgłosić błąd. \n\nZaleca się ponowne uruchomienie aplikacji." />
    <Entry Key="UI_ADVANCEMENT" Val="Awansowanie" />
    <Entry Key="UI_TUTORIAL_ADVANCEMENT1" Val="Ten ekran pozwala ci wydać dowolne Punkty Awansu ({ICON:AdvancementPointIcon}) na nowe materiały, przepisy rzemieślnicze i budynki." />
    <Entry Key="UI_TUTORIAL_ADVANCEMENT2" Val="Naciśnij te przyciski, aby wyświetlić każdą kategorię:" />
    <Entry Key="UI_TUTORIAL_ADVANCEMENT3" Val="Koszt odblokowania każdego przepisu jest wyświetlany obok jego ikony." />
    <Entry Key="UI_TUTORIAL_ADVANCEMENT4" Val="Materiały w {COLOR:yellow}przepisach na sprzęt {END_COLOR}odblokowują w losowej kolejności każdą rozgrywkę, ale możesz zobaczyć szczegóły zanim wydasz swoje Punkty Awansu klikając na przepis." />
    <Entry Key="UI_TUTORIAL_ADVANCEMENT5" Val="Każdy przepis wymaga odblokowania co najmniej jednego węzła nadrzędnego, który do niego prowadzi." />
    <Entry Key="UI_TUTORIAL_ADVANCEMENT6" Val="Na przykład Kryształowe Drewno można uzyskać tylko po odblokowaniu Diamentu lub Starożytnego Drewna." />
    <Entry Key="UI_TUTORIAL_ADVANCEMENT7" Val="Punkty Awansu {ICON:AdvancementPointIcon}są przyznawane za każdym razem, gdy zbierzesz wystarczającą liczbę Punktów Badawczych (RP)." />
    <Entry Key="UI_TUTORIAL_ADVANCEMENT8" Val="RP są wydawane po ukończeniu wydarzeń, zbudowaniu szkoły lub zbadaniu terenu i artefaktów istot." />
    <Entry Key="UI_STAY_IN_GAME" Val="Zostań w grze" />
    <Entry Key="UI_EXIT_GAME" Val="Wyjdź z gry" />
    <Entry Key="UI_CONNECTION_LOST" Val="Połączenie utracone" />
    <Entry Key="UI_SELECT_CATEGORY" Val="Wybierz kategorię" />
    <Entry Key="UI_SAVE_DELETE_WARNING" Val="Czy na pewno chcesz usunąć ten plik składowania?" />
    <Entry Key="UI_CUSTOM_DB_IN_USE" Val="Używasz starszej bazy danych. Jeśli chcesz rozpocząć nową grę, zaleca się przejście do bieżącej bazy danych. Wymaga to ponownego uruchomienia gry." />
    <Entry Key="UI_SWITCH_AND_EXIT" Val="Przełącz i wyjdź" />
    <Entry Key="UI_START_ANYWAY" Val="Start Anyway" />
    <Entry Key="UI_VALUE_SORT" Val="Sortuj według wartości" />
    <Entry Key="UI_WEIGHT_SORT" Val="Sortuj według wagi" />
    <Entry Key="UI_WEIGHT_TOTAL_SORT" Val="Sortuj według całkowitej wagi" />
    <Entry Key="UI_SKILL_LVL_SORT" Val="Sortuj według poziomu umiejętności" />
    <Entry Key="UI_DEV_HEAL_GROUP" Val="Grupa lecząca" />
    <Entry Key="UI_EASY" Val="Łatwy" />
    <Entry Key="UI_NORMAL" Val="Normalny" />
    <Entry Key="UI_DIFFICULT" Val="Trudne" />
    <Entry Key="UI_HARD" Val="Trudno" />
    <Entry Key="UI_CUSTOM" Val="Niestandardowy" />
    <Entry Key="UI_FINAL_SCORE_MULTIPLIER" Val="Mnożnik wyniku końcowego:" />
    <Entry Key="UI_PRESETS" Val="Ustawienia wstępne" />
    <Entry Key="UI_BASE_GROUP" Val="Grupa podstawowa" />
    <Entry Key="UI_CHARACTER_GROUP_CARRY" Val="Group Carry Bonus Per Character" />
    <Entry Key="UI_WORLD_PROGRESSION" Val="Światowy postęp" />
    <Entry Key="UI_TRUE" Val="Prawda" />
    <Entry Key="UI_FALSE" Val="Fałsz" />
    <Entry Key="UI_DISMANTLE_DIFFICULTY" Val="Dismantle Resource Recovery" />
    <Entry Key="UI_ROGUE_SPAWN" Val="Szybkość narastania grup nieuczciwych" />
    <Entry Key="UI_WORLD_SIZE" Val="Rozmiar świata" />
    <Entry Key="UI_RESOURCE_AVAILABILITY" Val="Dostępność zasobów" />
    <Entry Key="UI_RUINS" Val="Ruiny" />
    <Entry Key="UI_LOTS" Val="Wiele" />
    <Entry Key="UI_FEW" Val="Niewiele" />
    <Entry Key="UI_BASE_GROUP1" Val="2 x wojownik + 1 x dziecko" />
    <Entry Key="UI_BASE_GROUP2" Val="1 x wojownik + 1 x dziecko" />
    <Entry Key="UI_BASE_GROUP3" Val="1 x Dziecko" />
    <Entry Key="UI_CHARACTER_GROUP_CARRY_EASY" Val="600 Carry Bonus" />
    <Entry Key="UI_CHARACTER_GROUP_CARRY_NORMAL" Val="400 Carry Bonus" />
    <Entry Key="UI_CHARACTER_GROUP_CARRY_DIFFICULT" Val="200 Carry Bonus" />
    <Entry Key="UI_SLOW" Val="Wolno" />
    <Entry Key="UI_QUICK" Val="Szybki" />
    <Entry Key="UI_DISMANTLE_DIFFICULTY_30" Val="30 do 60%" />
    <Entry Key="UI_DISMANTLE_DIFFICULTY_20" Val="20 do 50%" />
    <Entry Key="UI_DISMANTLE_DIFFICULTY_10" Val="10 do 40%" />
    <Entry Key="UI_FREQUENT" Val="Częste" />
    <Entry Key="UI_SELDOM" Val="Rzadko" />
    <Entry Key="UI_SMALL" Val="Mały" />
    <Entry Key="UI_LARGE" Val="Duży" />
    <Entry Key="UI_ABUNDANT" Val="Obfite" />
    <Entry Key="UI_SPARSE" Val="Rzadki" />
    <Entry Key="UI_AUDIO_DRIVER_ERROR" Val="FMOD nie udało się zainicjować urządzenia wyjściowego. \n\nWydaje się, że wystąpił błąd sterownika audio. Jeśli problem nadal występuje, zainstaluj ponownie sterowniki audio i sprawdź, czy urządzenie dźwiękowe działa poprawnie." />
    <Entry Key="UI_VIEW_GROUPS" Val="Wyświetl grupy" />
    <Entry Key="UI_CANNOT_MODIFY_EQUIPMENT" Val="Nie możesz modyfikować swojego sprzętu podczas wydarzenia." />
    <Entry Key="UI_SAVE_GAME_VER_INCOMPATIBLE" Val="Oszczędność, którą próbujesz załadować, jest niezgodna z bieżącą wersją gry. Jeśli chcesz kontynuować grę, możesz skorzystać z oddziałów beta Steam, aby przywrócić kompatybilną wersję gry." />
    <Entry Key="UI_GATHERING_MAX_1PACK" Val="Zbieranie z przepełnieniem o połowę" />
    <Entry Key="UI_MADE_IN_GAME_VER" Val="Zapisane w wersji gry: " />
    <Entry Key="UI_PREVIOUS_GROUP" Val="Poprzednia grupa" />
    <Entry Key="UI_NEXT_GROUP" Val="Następna grupa" />
    <Entry Key="UI_CHARACTERS" Val="Postacie" />
    <Entry Key="UI_SHOW_QUEST_TRACKER" Val="Pokaż śledzenie misji" />
    <Entry Key="UI_SHOW_QUEST_TRACKER_DES" Val="Przydatna lista twoich aktualnych zadań." />
    <Entry Key="UI_RESEARCH_MATERIAL_ACQUIRED" Val="Zakupiony materiał badawczy!" />
    <Entry Key="UI_INDEX_ENEMIES" Val="Indeks - wrogowie" />
    <Entry Key="UI_INDEX_TERRAIN" Val="Indeks - teren" />
    <Entry Key="UI_INDEX" Val="Indeks" />
    <Entry Key="UI_THEOPEDIA" Val="Theopedia" />
    <Entry Key="UI_RESEARCH_MATERIAL_COLLECTED" Val="Zebrano materiał badawczy" />
    <Entry Key="UI_RESEARCH_COMPLETED_CHAR" Val="Zakończono badania - 15% premii za moc do wyzwań automatycznych względem tego stwora." />
    <Entry Key="UI_RESEARCH_COMPLETED_TERRAIN" Val="Badania zakończone." />
    <Entry Key="UI_DEFEATED" Val="Pokonany" />
    <Entry Key="UI_SKILLS_INNATE" Val="Umiejętności - Wrodzone" />
    <Entry Key="UI_SKILLS_FROM_EQUIPMENT" Val="Umiejętności - ze sprzętu" />
    <Entry Key="UI_RMB_SHOW_ENTITY_INFO" Val="{ICON:RMB}- wyświetl szczegóły" />
    <Entry Key="UI_FACTION_LOYALTY_CHANGED" Val="Lojalność frakcji zmieniła się:" />
    <Entry Key="UI_RESEARCH_SORT" Val="Sortuj według badań" />
    <Entry Key="UI_RESEARCH_ARTIFACTS" Val="Artefakty badawcze" />
    <Entry Key="UI_TUTORIAL_ARTIFACTS1" Val="Podczas wędrówki po świecie Thea napotkasz artefakty badawcze. Są one czasami zdobywane po wygranych wyzwaniach lub można je znaleźć w ziemi." />
    <Entry Key="UI_TUTORIAL_ARTIFACTS2" Val="Obóz w pobliżu Artefaktu Terenu pozwala go zebrać. Po zakończeniu gromadzenia zasób pojawi się w tym miejscu." />
    <Entry Key="UI_TUTORIAL_ARTIFACTS3" Val="Zebrany artefakt nie pojawia się w twoim ekwipunku, zamiast tego możesz go znaleźć na ekranie Badania, gdzie możesz przypisać ludzi do prowadzenia prac badawczych. \n\nArtefakty terenu i stworzenia odblokowują nowe wpisy wiedzy w Theopedii." />
    <Entry Key="UI_FACTION_FRIENDLY" Val="Przyjazny" />
    <Entry Key="UI_FACTION_NEUTRAL" Val="Neutralny" />
    <Entry Key="UI_FACTION_HOSTILE" Val="Wrogie" />
    <Entry Key="UI_ITS_SPRING" Val="Jest wiosna!" />
    <Entry Key="UI_ITS_SUMMER" Val="Jest lato!" />
    <Entry Key="UI_ITS_AUTUMN" Val="Jest jesień!" />
    <Entry Key="UI_ITS_WINTER" Val="Jest zima!" />
    <Entry Key="UI_SEASONAL_EFFECTS" Val="Efekty sezonowe:" />
    <Entry Key="UI_POSSIBLE_WEATHER_CONDITIONS" Val="Możliwe warunki pogodowe:" />
    <Entry Key="UI_SPRING_EFFECT1" Val="Zwiększone odzyskiwanie zdrowia, poczytalności i wiary" />
    <Entry Key="UI_SUMMER_EFFECT1" Val="Gromadzenie daje +0,5 PD w każdej turze" />
    <Entry Key="UI_AUTUMN_EFFECT1" Val="Crafting jest o 25% szybszy" />
    <Entry Key="UI_AUTUMN_EFFECT2" Val="Wrogowie są tak agresywni jak w nocy" />
    <Entry Key="UI_WINTER_EFFECT1" Val="Zdobywanie punktów doświadczenia z wydarzeń podwojonych dla wszystkich postaci" />
    <Entry Key="UI_WINTER_EFFECT2" Val="Wrogowie są tak agresywni jak w nocy" />
    <Entry Key="UI_WINTER_EFFECT3" Val="Szansa na pojawienie się gniazd Monster jest wyższa" />
    <Entry Key="UI_WINTER_EFFECT4" Val="Obozy i wioski zużywają 2 paliwo na turę zamiast 1" />
    <Entry Key="UI_WINTER_EFFECT5" Val="Odzyskiwanie Zdrowia, Poczytalności lub Wiary wymaga napędzanego obozu lub wioski" />
    <Entry Key="UI_WINTER_EFFECT6" Val="Zbieranie żywności i zasobów rzemieślniczych jest trudniejsze" />
    <Entry Key="UI_TRAITS" Val="Cechy" />
    <Entry Key="UI_COMPOSITE_INFO" Val="Ten zasób jest złożony i można go utworzyć na panelu Gotowanie i kompozyty." />
    <Entry Key="UI_INVENTORY_SHIFT" Val="- stos transferowy" />
    <Entry Key="UI_SEASONS" Val="Pory roku" />
    <Entry Key="UI_ONLY_POSITIVE_EFFECTS" Val="Tylko pozytywne efekty" />
    <Entry Key="UI_ALL_SEASONS_EFFECTS" Val="Wszystkie efekty sezonowe" />
    <Entry Key="UI_PARTICIPATING_GROUPS" Val="Grupy uczestniczące" />
    <Entry Key="UI_TUTORIAL_EVENTS1" Val="Spotkałeś się z wydarzeniem. Większość zdarzeń ma miejsce losowo na końcu tury lub podczas poruszania się po mapie." />
    <Entry Key="UI_TUTORIAL_EVENTS2" Val="Jeśli wydarzenie jest wyzwalane przez grupę znajdującą się na lądzie, dołączają również {COLOR:yellow}inne grupy w zasięgu 6 pól. {END_COLOR}" />
    <Entry Key="UI_TUTORIAL_EVENTS3" Val="Kliknij przycisk Wyświetl grupę, aby zobaczyć, które grupy biorą udział w wydarzeniu." />
    <Entry Key="UI_TUTORIAL_EVENTS4" Val="Pod każdą częścią opowieści zobaczysz jedną lub więcej możliwych odpowiedzi." />
    <Entry Key="UI_TUTORIAL_EVENTS5" Val="Niektóre odpowiedzi są widoczne tylko wtedy, gdy grupa spełnia określony warunek, tj. Zawiera określony typ znaku." />
    <Entry Key="UI_TUTORIAL_EVENTS6" Val="Jeśli widzisz którykolwiek z tych symboli:" />
    <Entry Key="UI_TUTORIAL_EVENTS7" Val="oznacza to, że ta konkretna odpowiedź doprowadzi do walki, więc uważnie przeczytaj odpowiedzi!" />
    <Entry Key="UI_SHOW_RESOURCE" Val="Pokaż zasoby!" />
    <Entry Key="UI_MAP_OF_THEA" Val="Mapa Thea" />
    <Entry Key="UI_WORLD" Val="Świat" />
    <Entry Key="UI_ISLAND" Val="Wyspa" />
    <Entry Key="UI_NOTE" Val="Uwaga" />
    <Entry Key="UI_BUILDINGS_FILTER" Val="Budynki" />
    <Entry Key="UI_EQUIPMENT_FILTER" Val="Sprzęt" />
    <Entry Key="UI_SHIPS_FILTER" Val="Statki" />
    <Entry Key="UI_PRODUCTION_COST_SORT" Val="Sortuj według kosztu produkcji" />
    <Entry Key="UI_LUCK_SORT" Val="Sortuj według szczęścia" />
    <Entry Key="UI_DOMINATION_VICTORY" Val="Zwycięstwo dominacji" />
    <Entry Key="UI_DOMINATION_VICTORY_DES" Val="Aby osiągnąć Zwycięstwo Dominacji, musisz spełnić jedno wymaganie w każdej z tych trzech kategorii:" />
    <Entry Key="UI_DOMINATION_1A" Val="Podbił co najmniej połowę osiedli frakcji." />
    <Entry Key="UI_DOMINATION_1B" Val="Przyjazny z co najmniej 5 frakcjami (Lojalność na poziomie 50 lub wyższym)." />
    <Entry Key="UI_DOMINATION_2A" Val="Masz co najmniej 20 obserwujących." />
    <Entry Key="UI_DOMINATION_2B" Val="Miej co najmniej 7 różnych ras wśród swoich zwolenników." />
    <Entry Key="UI_DOMINATION_3A" Val="Mieć co najmniej 6 budynków o poziomie umiejętności 4." />
    <Entry Key="UI_DOMINATION_3B" Val="Mieć co najmniej 6 znaków na poziomie 20." />
    <Entry Key="UI_CURRENTLY_CONQUERED" Val="Obecnie zdobyte:" />
    <Entry Key="UI_CURRENTLY_LOYAL" Val="Obecnie lojalni:" />
    <Entry Key="UI_FOLLOWERS" Val="Obserwujący:" />
    <Entry Key="UI_DIFFERENT_RACES" Val="Różne rasy:" />
    <Entry Key="UI_OWNED_LV4_BUILDINGS" Val="Posiadane budynki poziomu 4:" />
    <Entry Key="UI_CHARACTERS_ON_LVL20" Val="Postacie na poziomie 20:" />
    <Entry Key="UI_OR" Val="LUB" />
    <Entry Key="UI_GROUP_POINTS" Val="Maksymalny całkowity koszt cech" />
    <Entry Key="UI_STARTING_SEASON" Val="Sezon startowy" />
    <Entry Key="UI_SUMMER" Val="Lato" />
    <Entry Key="UI_AUTUMN" Val="Jesień" />
    <Entry Key="UI_WINTER" Val="Zima" />
    <Entry Key="UI_RARITY_SORT" Val="Sortuj według rzadkości" />
    <Entry Key="UI_UNLOCKED" Val="Odblokowany" />
    <Entry Key="UI_LOCKED" Val="Zablokowany" />
    <Entry Key="UI_MATCHING" Val="Dopasowanie" />
    <Entry Key="UI_CHARACTERS_FILTER" Val="Tylko znaki" />
    <Entry Key="UI_DOMAIN_SORT" Val="Sortuj według domeny" />
    <Entry Key="UI_COST_SORT" Val="Sortuj według kosztów" />
    <Entry Key="UI_ACTIVE_QUESTS" Val="Aktywne misje" />
    <Entry Key="UI_PARENT_UNLOCK_REQUIRED" Val="{COLOR:#C80000}Musisz najpierw odblokować awans rodzica." />
    <Entry Key="UI_CURRENT_TRADE_VALUE" Val="Aktualne saldo:" />
    <Entry Key="UI_ALLOW_SAVES" Val="Ręczne zapisywanie" />
    <Entry Key="UI_ALLOW_CUSTOM_SAVES" Val="Dozwolone" />
    <Entry Key="UI_DISALLOW_CUSTOM_SAVES" Val="Niedozwolone" />
    <Entry Key="UI_SAVE_AND_QUIT" Val="Zapisz i zakończ" />
    <Entry Key="UI_FINISHED_QUESTS" Val="Zakończone misje" />
    <Entry Key="UI_CHALLENGE_DIFFICULTY_INCREASE" Val="Zwiększenie trudności wyzwania" />
    <Entry Key="UI_NYIA_UNLOCKED" Val="Nyja odblokowana!" />
    <Entry Key="UI_TRIGLAV_UNLOCKED" Val="Trzygłów odblokowany!" />
    <Entry Key="UI_COAL_REMOVED_FROM_FIRST_ISLAND" Val="Węgiel usunięty z początkowej wyspy" />
    <Entry Key="UI_SKIP_TO_RESOLUTION" Val="Przejdź do rozdzielczości" />
    <Entry Key="UI_ARE_YOU_SURE_SKIP_TO_RESOLUTION" Val="Czy na pewno chcesz zakończyć rzucanie kart w tej rundzie i przejść do rozdzielczości? Twój wróg normalnie zagra swoje karty." />
    <Entry Key="UI_STRENGTH_CHARACTER_SORT" Val="Sortuj według siły" />
    <Entry Key="UI_PERCEPTION_CHARACTER_SORT" Val="Sortuj według postrzegania" />
    <Entry Key="UI_INTELLIGENCE_CHARACTER_SORT" Val="Sortuj według wywiadu" />
    <Entry Key="UI_WISDOM_CHARACTER_SORT" Val="Sortuj według mądrości" />
    <Entry Key="UI_MYSTICISM_CHARACTER_SORT" Val="Sortuj według mistycyzmu" />
    <Entry Key="UI_DESTINY_CHARACTER_SORT" Val="Sortuj według przeznaczenia" />
    <Entry Key="UI_CRAFTING_CHARACTER_SORT" Val="Sortuj według rzemiosła" />
    <Entry Key="UI_RESEARCH_CHARACTER_SORT" Val="Sortuj według badań" />
    <Entry Key="UI_RITUALS_CHARACTER_SORT" Val="Sortuj według rytuałów" />
    <Entry Key="UI_CLASS_CHARACTER_SORT" Val="Sortuj według klasy" />
    <Entry Key="UI_CARRY_LIMIT_CHARACTER_SORT" Val="Sortuj według Carry Limit" />
    <Entry Key="UI_AUTOSELECT" Val="Automatyczny wybór" />
    <Entry Key="UI_INFORMATION" Val="Informacje" />
    <Entry Key="UI_TUTORIALS_RESET" Val="Samouczki zostały zresetowane." />
    <Entry Key="UI_LEVEL_CHARACTER_SORT" Val="Sortuj według poziomu" />
    <Entry Key="UI_VILLAGERS" Val="Wieśniacy" />
    <Entry Key="UI_FUEL" Val="Paliwo" />
    <Entry Key="UI_BUILDINGS_SHIPS" Val="Budynki i statki" />
    <Entry Key="UI_LUCK_CHARACTER_SORT" Val="Sortuj według szczęścia" />
    <Entry Key="UI_ESSENCE_AMOUNT_SORT" Val="Sortuj według kwoty esencji" />
    <Entry Key="UI_ESSENCE_TYPE_SORT" Val="Sortuj według typu esencji" />
    <Entry Key="UI_AUTORESOLVE_PROFICIENCY" Val="Autoresolve Proficiency" />
    <Entry Key="UI_GOOD" Val="Dobrze" />
    <Entry Key="UI_POOR" Val="Biedny" />
    <Entry Key="UI_SWITCHING_DATABASE" Val="Zalecamy korzystanie z najnowszej wersji plików bazy danych i powrót do innej wersji, jeśli wiesz, co robisz. Upewnij się, że wersje gier są zgodne, użycie niewłaściwej bazy danych może spowodować awarie! Jeśli chcesz kontynuować grę zapisaną w poprzedniej wersji gry, przełącz się na poprzednią wersję, używając gałęzi beta." />
    <Entry Key="UI_PATCH_NOTES" Val="Uwagi do poprawki" />
    <Entry Key="UI_TAB_TO_SWITCH" Val="TAB - przełączanie między grupami" />
    <Entry Key="UI_SEE_RESULTS" Val="Zobacz wyniki" />
    <Entry Key="UI_LESS" Val="Mniej" />
    <Entry Key="UI_ADDED_TO_PROFILE" Val="Dodano do profilu:" />
    <Entry Key="UI_CLAIM" Val="Punkty roszczenia" />
    <Entry Key="UI_TOTAL_VALUE" Val="Łączna wartość:" />
    <Entry Key="UI_SELECT_LANGUAGE" Val="Select Language" />
    <Entry Key="UI_LOADING_FILES_FROM_CLOUD_FAILED" Val="Loading files from could has failed, possibly something is blocking drive access.\n\nWarning - data loss may occur! Please contact us on bugs@muhagames.com and we will try to help you resolve your issue." />
    <Entry Key="UI_LOCAL_AND_CLOUD_IS_DIFFERENT" Val="Files on your local drive and in the cloud share the same name but are out of sync, which version would you like to keep?\n\n(Note: saves/profiles removed or lost on one computer will not be removed from the other. To prevent data loss, you will have to remove them again on the other computer if you wish.)" />
    <Entry Key="UI_USE_CLOUD" Val="Use Cloud" />
    <Entry Key="UI_USE_LOCAL" Val="Use Local" />
    <Entry Key="UI_MODS" Val="Mods" />
    <Entry Key="UI_MOVE_UP" Val="Move Up" />
    <Entry Key="UI_MOVE_DOWN" Val="Move Down" />
    <Entry Key="UI_MOD_MANAGER" Val="Mod Manager" />
    <Entry Key="UI_PUBLISH" Val="Publish" />
    <Entry Key="UI_DESCRIPTION" Val="Description" />
    <Entry Key="UI_AUTHOR" Val="Author:" />
    <Entry Key="UI_VISIBILITY" Val="Visibility:" />
    <Entry Key="UI_CHANGES_TO_HAVE_EFFECT" Val="Please restart the application for the changes to take effect." />
    <Entry Key="UI_LATER" Val="Later" />
    <Entry Key="UI_PUBLIC" Val="Public" />
    <Entry Key="UI_FRIENDS_ONLY" Val="Friends Only" />
    <Entry Key="UI_PRIVATE" Val="Private" />
    <Entry Key="UI_INCORRECT_VALUE" Val="{COLOR:yellow}Incorrect Value{END_COLOR}" />
  </LOC_LIBRARY-UI>
</DATABASE_UI_LOCALIZATION-NO_HSH>